Workbook

Sheet Revenue Detail
A1: Revenue Detail — FY2027 Budget vs. Actual (by Month, Region, Product Line)
A3: Month | B3: Region | C3: Product Line | D3: Budgeted Units | E3: Budgeted Unit Price | F3: Budgeted Revenue | G3: Actual Units | H3: Actual Unit Price | I3: Actual Revenue | J3: Variance $ | K3: Variance % | L3: Month # | M3: Sales Channel | N3: YTD Actual Revenue | O3: % of FY Budget Achieved (YTD) | P3: Notes
A4: Jan | B4: Northeast | C4: Apparel | D4: 1804 | E4: 45 | F4: =D4*E4 -> 81180 | G4: 1872 | H4: 44.16 | I4: =G4*H4 -> 82667.52 | J4: =I4-F4 -> 1487.52 | K4: =IFERROR(J4/F4,0) -> 0.018323725 | L4: 1 | M4: Retail Stores | N4: =SUMIFS($I$4:$I$195,$B$4:$B$195,B4,$C$4:$C$195,C4,$L$4:$L$195,"<="&L4) -> 82667.52 | O4: =IFERROR(N4/SUMIFS($F$4:$F$195,$B$4:$B$195,B4,$C$4:$C$195,C4),0) -> 0.064515293
A5: Jan | B5: Northeast | C5: Home Goods | D5: 1082 | E5: 65 | F5: =D5*E5 -> 70330 | G5: 1033 | H5: 66.09 | I5: =G5*H5 -> 68270.97 | J5: =I5-F5 -> -2059.03 | K5: =IFERROR(J5/F5,0) -> -0.029276696 | L5: 1 | M5: E-Commerce | N5: =SUMIFS($I$4:$I$195,$B$4:$B$195,B5,$C$4:$C$195,C5,$L$4:$L$195,"<="&L5) -> 68270.97 | O5: =IFERROR(N5/SUMIFS($F$4:$F$195,$B$4:$B$195,B5,$C$4:$C$195,C5),0) -> 0.061476387
A6: Jan | B6: Northeast | C6: Electronics | D6: 451 | E6: 220 | F6: =D6*E6 -> 99220 | G6: 491 | H6: 216.56 | I6: =G6*H6 -> 106330.96 | J6: =I6-F6 -> 7110.96 | K6: =IFERROR(J6/F6,0) -> 0.071668615 | L6: 1 | M6: Retail Stores | N6: =SUMIFS($I$4:$I$195,$B$4:$B$195,B6,$C$4:$C$195,C6,$L$4:$L$195,"<="&L6) -> 106330.96 | O6: =IFERROR(N6/SUMIFS($F$4:$F$195,$B$4:$B$195,B6,$C$4:$C$195,C6),0) -> 0.067888435
A7: Jan | B7: Northeast | C7: Outdoor | D7: 722 | E7: 95 | F7: =D7*E7 -> 68590 | G7: 661 | H7: 94.14 | I7: =G7*H7 -> 62226.54 | J7: =I7-F7 -> -6363.46 | K7: =IFERROR(J7/F7,0) -> -0.092775332 | L7: 1 | M7: E-Commerce | N7: =SUMIFS($I$4:$I$195,$B$4:$B$195,B7,$C$4:$C$195,C7,$L$4:$L$195,"<="&L7) -> 62226.54 | O7: =IFERROR(N7/SUMIFS($F$4:$F$195,$B$4:$B$195,B7,$C$4:$C$195,C7),0) -> 0.05750787
A8: Jan | B8: Midwest | C8: Apparel | D8: 1443 | E8: 45 | F8: =D8*E8 -> 64935 | G8: 1321 | H8: 44.55 | I8: =G8*H8 -> 58850.55 | J8: =I8-F8 -> -6084.45 | K8: =IFERROR(J8/F8,0) -> -0.093700624 | L8: 1 | M8: E-Commerce | N8: =SUMIFS($I$4:$I$195,$B$4:$B$195,B8,$C$4:$C$195,C8,$L$4:$L$195,"<="&L8) -> 58850.55 | O8: =IFERROR(N8/SUMIFS($F$4:$F$195,$B$4:$B$195,B8,$C$4:$C$195,C8),0) -> 0.057410085
A9: Jan | B9: Midwest | C9: Home Goods | D9: 866 | E9: 65 | F9: =D9*E9 -> 56290 | G9: 882 | H9: 64.42 | I9: =G9*H9 -> 56818.44 | J9: =I9-F9 -> 528.44 | K9: =IFERROR(J9/F9,0) -> 0.0093878131 | L9: 1 | M9: E-Commerce | N9: =SUMIFS($I$4:$I$195,$B$4:$B$195,B9,$C$4:$C$195,C9,$L$4:$L$195,"<="&L9) -> 56818.44 | O9: =IFERROR(N9/SUMIFS($F$4:$F$195,$B$4:$B$195,B9,$C$4:$C$195,C9),0) -> 0.06395456
A10: Jan | B10: Midwest | C10: Electronics | D10: 361 | E10: 220 | F10: =D10*E10 -> 79420 | G10: 387 | H10: 215.67 | I10: =G10*H10 -> 83464.29 | J10: =I10-F10 -> 4044.29 | K10: =IFERROR(J10/F10,0) -> 0.050922815 | L10: 1 | M10: E-Commerce | N10: =SUMIFS($I$4:$I$195,$B$4:$B$195,B10,$C$4:$C$195,C10,$L$4:$L$195,"<="&L10) -> 83464.29 | O10: =IFERROR(N10/SUMIFS($F$4:$F$195,$B$4:$B$195,B10,$C$4:$C$195,C10),0) -> 0.066615828
A11: Jan | B11: Midwest | C11: Outdoor | D11: 577 | E11: 95 | F11: =D11*E11 -> 54815 | G11: 606 | H11: 94.72 | I11: =G11*H11 -> 57400.32 | J11: =I11-F11 -> 2585.32 | K11: =IFERROR(J11/F11,0) -> 0.047164462 | L11: 1 | M11: Retail Stores | N11: =SUMIFS($I$4:$I$195,$B$4:$B$195,B11,$C$4:$C$195,C11,$L$4:$L$195,"<="&L11) -> 57400.32 | O11: =IFERROR(N11/SUMIFS($F$4:$F$195,$B$4:$B$195,B11,$C$4:$C$195,C11),0) -> 0.066316907
A12: Jan | B12: South | C12: Apparel | D12: 1640 | E12: 45 | F12: =D12*E12 -> 73800 | G12: 1806 | H12: 44.86 | I12: =G12*H12 -> 81017.16 | J12: =I12-F12 -> 7217.16 | K12: =IFERROR(J12/F12,0) -> 0.097793496 | L12: 1 | M12: Retail Stores | N12: =SUMIFS($I$4:$I$195,$B$4:$B$195,B12,$C$4:$C$195,C12,$L$4:$L$195,"<="&L12) -> 81017.16 | O12: =IFERROR(N12/SUMIFS($F$4:$F$195,$B$4:$B$195,B12,$C$4:$C$195,C12),0) -> 0.069550053
A13: Jan | B13: South | C13: Home Goods | D13: 984 | E13: 65 | F13: =D13*E13 -> 63960 | G13: 914 | H13: 66.45 | I13: =G13*H13 -> 60735.3 | J13: =I13-F13 -> -3224.7 | K13: =IFERROR(J13/F13,0) -> -0.050417448 | L13: 1 | M13: E-Commerce | N13: =SUMIFS($I$4:$I$195,$B$4:$B$195,B13,$C$4:$C$195,C13,$L$4:$L$195,"<="&L13) -> 60735.3 | O13: =IFERROR(N13/SUMIFS($F$4:$F$195,$B$4:$B$195,B13,$C$4:$C$195,C13),0) -> 0.060159754
A14: Jan | B14: South | C14: Electronics | D14: 410 | E14: 220 | F14: =D14*E14 -> 90200 | G14: 439 | H14: 223.63 | I14: =G14*H14 -> 98173.57 | J14: =I14-F14 -> 7973.57 | K14: =IFERROR(J14/F14,0) -> 0.08839878 | L14: 1 | M14: E-Commerce | N14: =SUMIFS($I$4:$I$195,$B$4:$B$195,B14,$C$4:$C$195,C14,$L$4:$L$195,"<="&L14) -> 98173.57 | O14: =IFERROR(N14/SUMIFS($F$4:$F$195,$B$4:$B$195,B14,$C$4:$C$195,C14),0) -> 0.068953057
A15: Jan | B15: South | C15: Outdoor | D15: 656 | E15: 95 | F15: =D15*E15 -> 62320 | G15: 725 | H15: 94.9 | I15: =G15*H15 -> 68802.5 | J15: =I15-F15 -> 6482.5 | K15: =IFERROR(J15/F15,0) -> 0.10401958 | L15: 1 | M15: E-Commerce | N15: =SUMIFS($I$4:$I$195,$B$4:$B$195,B15,$C$4:$C$195,C15,$L$4:$L$195,"<="&L15) -> 68802.5 | O15: =IFERROR(N15/SUMIFS($F$4:$F$195,$B$4:$B$195,B15,$C$4:$C$195,C15),0) -> 0.069943707
... A23: Feb | B23: Northeast | C23: Outdoor | D23: 739 | E23: 95.24 | F23: =D23*E23 -> 70382.36 | G23: 780 | H23: 94.11 | I23: =G23*H23 -> 73405.8 | J23: =I23-F23 -> 3023.44 | K23: =IFERROR(J23/F23,0) -> 0.042957355 | L23: 2 | M23: Retail Stores | N23: =SUMIFS($I$4:$I$195,$B$4:$B$195,B23,$C$4:$C$195,C23,$L$4:$L$195,"<="&L23) -> 135632.34 | O23: =IFERROR(N23/SUMIFS($F$4:$F$195,$B$4:$B$195,B23,$C$4:$C$195,C23),0) -> 0.12534727
A24: Feb | B24: Midwest | C24: Apparel | D24: 1478 | E24: 45.11 | F24: =D24*E24 -> 66672.58 | G24: 1637 | H24: 45.65 | I24: =G24*H24 -> 74729.05 | J24: =I24-F24 -> 8056.47 | K24: =IFERROR(J24/F24,0) -> 0.12083633 | L24: 2 | M24: E-Commerce | N24: =SUMIFS($I$4:$I$195,$B$4:$B$195,B24,$C$4:$C$195,C24,$L$4:$L$195,"<="&L24) -> 133579.6 | O24: =IFERROR(N24/SUMIFS($F$4:$F$195,$B$4:$B$195,B24,$C$4:$C$195,C24),0) -> 0.13031002 | P24: Promotional lift exceeded expectations for this line.
A25: Feb | B25: Midwest | C25: Home Goods | D25: 887 | E25: 65.16 | F25: =D25*E25 -> 57796.92 | G25: 865 | H25: 66.36 | I25: =G25*H25 -> 57401.4 | J25: =I25-F25 -> -395.52 | K25: =IFERROR(J25/F25,0) -> -0.0068432712 | L25: 2 | M25: Retail Stores | N25: =SUMIFS($I$4:$I$195,$B$4:$B$195,B25,$C$4:$C$195,C25,$L$4:$L$195,"<="&L25) -> 114219.84 | O25: =IFERROR(N25/SUMIFS($F$4:$F$195,$B$4:$B$195,B25,$C$4:$C$195,C25),0) -> 0.1285653
A26: Feb | B26: Midwest | C26: Electronics | D26: 370 | E26: 220.55 | F26: =D26*E26 -> 81603.5 | G26: 398 | H26: 225.02 | I26: =G26*H26 -> 89557.96 | J26: =I26-F26 -> 7954.46 | K26: =IFERROR(J26/F26,0) -> 0.097476946 | L26: 2 | M26: Retail Stores | N26: =SUMIFS($I$4:$I$195,$B$4:$B$195,B26,$C$4:$C$195,C26,$L$4:$L$195,"<="&L26) -> 173022.25 | O26: =IFERROR(N26/SUMIFS($F$4:$F$195,$B$4:$B$195,B26,$C$4:$C$195,C26),0) -> 0.13809523
A27: Feb | B27: Midwest | C27: Outdoor | D27: 591 | E27: 95.24 | F27: =D27*E27 -> 56286.84 | G27: 546 | H27: 97.68 | I27: =G27*H27 -> 53333.28 | J27: =I27-F27 -> -2953.56 | K27: =IFERROR(J27/F27,0) -> -0.052473367 | L27: 2 | M27: E-Commerce | N27: =SUMIFS($I$4:$I$195,$B$4:$B$195,B27,$C$4:$C$195,C27,$L$4:$L$195,"<="&L27) -> 110733.6 | O27: =IFERROR(N27/SUMIFS($F$4:$F$195,$B$4:$B$195,B27,$C$4:$C$195,C27),0) -> 0.127935
A28: Feb | B28: South | C28: Apparel | D28: 1680 | E28: 45.11 | F28: =D28*E28 -> 75784.8 | G28: 1770 | H28: 44.69 | I28: =G28*H28 -> 79101.3 | J28: =I28-F28 -> 3316.5 | K28: =IFERROR(J28/F28,0) -> 0.043762074 | L28: 2 | M28: E-Commerce | N28: =SUMIFS($I$4:$I$195,$B$4:$B$195,B28,$C$4:$C$195,C28,$L$4:$L$195,"<="&L28) -> 160118.46 | O28: =IFERROR(N28/SUMIFS($F$4:$F$195,$B$4:$B$195,B28,$C$4:$C$195,C28),0) -> 0.13745542
A29: Feb | B29: South | C29: Home Goods | D29: 1008 | E29: 65.16 | F29: =D29*E29 -> 65681.28 | G29: 1096 | H29: 65.95 | I29: =G29*H29 -> 72281.2 | J29: =I29-F29 -> 6599.92 | K29: =IFERROR(J29/F29,0) -> 0.10048403 | L29: 2 | M29: Retail Stores | N29: =SUMIFS($I$4:$I$195,$B$4:$B$195,B29,$C$4:$C$195,C29,$L$4:$L$195,"<="&L29) -> 133016.5 | O29: =IFERROR(N29/SUMIFS($F$4:$F$195,$B$4:$B$195,B29,$C$4:$C$195,C29),0) -> 0.131756
A30: Feb | B30: South | C30: Electronics | D30: 420 | E30: 220.55 | F30: =D30*E30 -> 92631 | G30: 394 | H30: 224.35 | I30: =G30*H30 -> 88393.9 | J30: =I30-F30 -> -4237.1 | K30: =IFERROR(J30/F30,0) -> -0.045741706 | L30: 2 | M30: E-Commerce | N30: =SUMIFS($I$4:$I$195,$B$4:$B$195,B30,$C$4:$C$195,C30,$L$4:$L$195,"<="&L30) -> 186567.47 | O30: =IFERROR(N30/SUMIFS($F$4:$F$195,$B$4:$B$195,B30,$C$4:$C$195,C30),0) -> 0.13103728
A31: Feb | B31: South | C31: Outdoor | D31: 672 | E31: 95.24 | F31: =D31*E31 -> 64001.28 | G31: 712 | H31: 95.38 | I31: =G31*H31 -> 67910.56 | J31: =I31-F31 -> 3909.28 | K31: =IFERROR(J31/F31,0) -> 0.061081278 | L31: 2 | M31: E-Commerce | N31: =SUMIFS($I$4:$I$195,$B$4:$B$195,B31,$C$4:$C$195,C31,$L$4:$L$195,"<="&L31) -> 136713.06 | O31: =IFERROR(N31/SUMIFS($F$4:$F$195,$B$4:$B$195,B31,$C$4:$C$195,C31),0) -> 0.13898068
A32: Feb | B32: West | C32: Apparel | D32: 1982 | E32: 45.11 | F32: =D32*E32 -> 89408.02 | G32: 1947 | H32: 46.46 | I32: =G32*H32 -> 90457.62 | J32: =I32-F32 -> 1049.6 | K32: =IFERROR(J32/F32,0) -> 0.011739439 | L32: 2 | M32: Retail Stores | N32: =SUMIFS($I$4:$I$195,$B$4:$B$195,B32,$C$4:$C$195,C32,$L$4:$L$195,"<="&L32) -> 185167.8 | O32: =IFERROR(N32/SUMIFS($F$4:$F$195,$B$4:$B$195,B32,$C$4:$C$195,C32),0) -> 0.13471124
A33: Feb | B33: West | C33: Home Goods | D33: 1189 | E33: 65.16 | F33: =D33*E33 -> 77475.24 | G33: 1199 | H33: 66.32 | I33: =G33*H33 -> 79517.68 | J33: =I33-F33 -> 2042.44 | K33: =IFERROR(J33/F33,0) -> 0.026362487 | L33: 2 | M33: Wholesale | N33: =SUMIFS($I$4:$I$195,$B$4:$B$195,B33,$C$4:$C$195,C33,$L$4:$L$195,"<="&L33) -> 158111.77 | O33: =IFERROR(N33/SUMIFS($F$4:$F$195,$B$4:$B$195,B33,$C$4:$C$195,C33),0) -> 0.13272323
A34: Feb | B34: West | C34: Electronics | D34: 496 | E34: 220.55 | F34: =D34*E34 -> 109392.8 | G34: 467 | H34: 217.9 | I34: =G34*H34 -> 101759.3 | J34: =I34-F34 -> -7633.5 | K34: =IFERROR(J34/F34,0) -> -0.069780644 | L34: 2 | M34: E-Commerce | N34: =SUMIFS($I$4:$I$195,$B$4:$B$195,B34,$C$4:$C$195,C34,$L$4:$L$195,"<="&L34) -> 203054.44 | O34: =IFERROR(N34/SUMIFS($F$4:$F$195,$B$4:$B$195,B34,$C$4:$C$195,C34),0) -> 0.12085416
A35: Feb | B35: West | C35: Outdoor | D35: 793 | E35: 95.24 | F35: =D35*E35 -> 75525.32 | G35: 816 | H35: 95.17 | I35: =G35*H35 -> 77658.72 | J35: =I35-F35 -> 2133.4 | K35: =IFERROR(J35/F35,0) -> 0.02824748 | L35: 2 | M35: E-Commerce | N35: =SUMIFS($I$4:$I$195,$B$4:$B$195,B35,$C$4:$C$195,C35,$L$4:$L$195,"<="&L35) -> 146907.92 | O35: =IFERROR(N35/SUMIFS($F$4:$F$195,$B$4:$B$195,B35,$C$4:$C$195,C35),0) -> 0.12656325
A36: Mar | B36: Northeast | C36: Apparel | D36: 2046 | E36: 45.22 | F36: =D36*E36 -> 92520.12 | G36: 2053 | H36: 44.88 | I36: =G36*H36 -> 92138.64 | J36: =I36-F36 -> -381.48 | K36: =IFERROR(J36/F36,0) -> -0.0041232113 | L36: 3 | M36: E-Commerce | N36: =SUMIFS($I$4:$I$195,$B$4:$B$195,B36,$C$4:$C$195,C36,$L$4:$L$195,"<="&L36) -> 261128.67 | O36: =IFERROR(N36/SUMIFS($F$4:$F$195,$B$4:$B$195,B36,$C$4:$C$195,C36),0) -> 0.20378974
... A40: Mar | B40: Midwest | C40: Apparel | D40: 1637 | E40: 45.22 | F40: =D40*E40 -> 74025.14 | G40: 1491 | H40: 45.95 | I40: =G40*H40 -> 68511.45 | J40: =I40-F40 -> -5513.69 | K40: =IFERROR(J40/F40,0) -> -0.07448402 | L40: 3 | M40: E-Commerce | N40: =SUMIFS($I$4:$I$195,$B$4:$B$195,B40,$C$4:$C$195,C40,$L$4:$L$195,"<="&L40) -> 202091.05 | O40: =IFERROR(N40/SUMIFS($F$4:$F$195,$B$4:$B$195,B40,$C$4:$C$195,C40),0) -> 0.19714454
A41: Mar | B41: Midwest | C41: Home Goods | D41: 982 | E41: 65.32 | F41: =D41*E41 -> 64144.24 | G41: 1084 | H41: 66.5 | I41: =G41*H41 -> 72086 | J41: =I41-F41 -> 7941.76 | K41: =IFERROR(J41/F41,0) -> 0.12381096 | L41: 3 | M41: E-Commerce | N41: =SUMIFS($I$4:$I$195,$B$4:$B$195,B41,$C$4:$C$195,C41,$L$4:$L$195,"<="&L41) -> 186305.84 | O41: =IFERROR(N41/SUMIFS($F$4:$F$195,$B$4:$B$195,B41,$C$4:$C$195,C41),0) -> 0.20970495 | P41: Strong sell-through; consider raising next year's unit forecast.
A42: Mar | B42: Midwest | C42: Electronics | D42: 409 | E42: 221.1 | F42: =D42*E42 -> 90429.9 | G42: 443 | H42: 219.98 | I42: =G42*H42 -> 97451.14 | J42: =I42-F42 -> 7021.24 | K42: =IFERROR(J42/F42,0) -> 0.077642904 | L42: 3 | M42: E-Commerce | N42: =SUMIFS($I$4:$I$195,$B$4:$B$195,B42,$C$4:$C$195,C42,$L$4:$L$195,"<="&L42) -> 270473.39 | O42: =IFERROR(N42/SUMIFS($F$4:$F$195,$B$4:$B$195,B42,$C$4:$C$195,C42),0) -> 0.21587446
A43: Mar | B43: Midwest | C43: Outdoor | D43: 655 | E43: 95.47 | F43: =D43*E43 -> 62532.85 | G43: 676 | H43: 94.29 | I43: =G43*H43 -> 63740.04 | J43: =I43-F43 -> 1207.19 | K43: =IFERROR(J43/F43,0) -> 0.019304893 | L43: 3 | M43: E-Commerce | N43: =SUMIFS($I$4:$I$195,$B$4:$B$195,B43,$C$4:$C$195,C43,$L$4:$L$195,"<="&L43) -> 174473.64 | O43: =IFERROR(N43/SUMIFS($F$4:$F$195,$B$4:$B$195,B43,$C$4:$C$195,C43),0) -> 0.20157644
A44: Mar | B44: South | C44: Apparel | D44: 1860 | E44: 45.22 | F44: =D44*E44 -> 84109.2 | G44: 1893 | H44: 46.08 | I44: =G44*H44 -> 87229.44 | J44: =I44-F44 -> 3120.24 | K44: =IFERROR(J44/F44,0) -> 0.037097488 | L44: 3 | M44: E-Commerce | N44: =SUMIFS($I$4:$I$195,$B$4:$B$195,B44,$C$4:$C$195,C44,$L$4:$L$195,"<="&L44) -> 247347.9 | O44: =IFERROR(N44/SUMIFS($F$4:$F$195,$B$4:$B$195,B44,$C$4:$C$195,C44),0) -> 0.21233847
A45: Mar | B45: South | C45: Home Goods | D45: 1116 | E45: 65.32 | F45: =D45*E45 -> 72897.12 | G45: 1016 | H45: 65.07 | I45: =G45*H45 -> 66111.12 | J45: =I45-F45 -> -6786 | K45: =IFERROR(J45/F45,0) -> -0.093090097 | L45: 3 | M45: Retail Stores | N45: =SUMIFS($I$4:$I$195,$B$4:$B$195,B45,$C$4:$C$195,C45,$L$4:$L$195,"<="&L45) -> 199127.62 | O45: =IFERROR(N45/SUMIFS($F$4:$F$195,$B$4:$B$195,B45,$C$4:$C$195,C45),0) -> 0.19724063
A46: Mar | B46: South | C46: Electronics | D46: 465 | E46: 221.1 | F46: =D46*E46 -> 102811.5 | G46: 510 | H46: 226.39 | I46: =G46*H46 -> 115458.9 | J46: =I46-F46 -> 12647.4 | K46: =IFERROR(J46/F46,0) -> 0.12301542 | L46: 3 | M46: E-Commerce | N46: =SUMIFS($I$4:$I$195,$B$4:$B$195,B46,$C$4:$C$195,C46,$L$4:$L$195,"<="&L46) -> 302026.37 | O46: =IFERROR(N46/SUMIFS($F$4:$F$195,$B$4:$B$195,B46,$C$4:$C$195,C46),0) -> 0.21213084 | P46: Outperformed plan on unexpected demand; monitor inventory levels.
A47: Mar | B47: South | C47: Outdoor | D47: 744 | E47: 95.47 | F47: =D47*E47 -> 71029.68 | G47: 713 | H47: 94.71 | I47: =G47*H47 -> 67528.23 | J47: =I47-F47 -> -3501.45 | K47: =IFERROR(J47/F47,0) -> -0.04929559 | L47: 3 | M47: E-Commerce | N47: =SUMIFS($I$4:$I$195,$B$4:$B$195,B47,$C$4:$C$195,C47,$L$4:$L$195,"<="&L47) -> 204241.29 | O47: =IFERROR(N47/SUMIFS($F$4:$F$195,$B$4:$B$195,B47,$C$4:$C$195,C47),0) -> 0.20762898
A48: Mar | B48: West | C48: Apparel | D48: 2195 | E48: 45.22 | F48: =D48*E48 -> 99257.9 | G48: 2032 | H48: 45.97 | I48: =G48*H48 -> 93411.04 | J48: =I48-F48 -> -5846.86 | K48: =IFERROR(J48/F48,0) -> -0.058905739 | L48: 3 | M48: E-Commerce | N48: =SUMIFS($I$4:$I$195,$B$4:$B$195,B48,$C$4:$C$195,C48,$L$4:$L$195,"<="&L48) -> 278578.84 | O48: =IFERROR(N48/SUMIFS($F$4:$F$195,$B$4:$B$195,B48,$C$4:$C$195,C48),0) -> 0.20266861
A49: Mar | B49: West | C49: Home Goods | D49: 1317 | E49: 65.32 | F49: =D49*E49 -> 86026.44 | G49: 1456 | H49: 65.75 | I49: =G49*H49 -> 95732 | J49: =I49-F49 -> 9705.56 | K49: =IFERROR(J49/F49,0) -> 0.11282066 | L49: 3 | M49: Retail Stores | N49: =SUMIFS($I$4:$I$195,$B$4:$B$195,B49,$C$4:$C$195,C49,$L$4:$L$195,"<="&L49) -> 253843.77 | O49: =IFERROR(N49/SUMIFS($F$4:$F$195,$B$4:$B$195,B49,$C$4:$C$195,C49),0) -> 0.21308321
A50: Mar | B50: West | C50: Electronics | D50: 549 | E50: 221.1 | F50: =D50*E50 -> 121383.9 | G50: 572 | H50: 227.15 | I50: =G50*H50 -> 129929.8 | J50: =I50-F50 -> 8545.9 | K50: =IFERROR(J50/F50,0) -> 0.0704039 | L50: 3 | M50: Retail Stores | N50: =SUMIFS($I$4:$I$195,$B$4:$B$195,B50,$C$4:$C$195,C50,$L$4:$L$195,"<="&L50) -> 332984.24 | O50: =IFERROR(N50/SUMIFS($F$4:$F$195,$B$4:$B$195,B50,$C$4:$C$195,C50),0) -> 0.19818592
A51: Mar | B51: West | C51: Outdoor | D51: 878 | E51: 95.47 | F51: =D51*E51 -> 83822.66 | G51: 892 | H51: 96.46 | I51: =G51*H51 -> 86042.32 | J51: =I51-F51 -> 2219.66 | K51: =IFERROR(J51/F51,0) -> 0.026480429 | L51: 3 | M51: Wholesale | N51: =SUMIFS($I$4:$I$195,$B$4:$B$195,B51,$C$4:$C$195,C51,$L$4:$L$195,"<="&L51) -> 232950.24 | O51: =IFERROR(N51/SUMIFS($F$4:$F$195,$B$4:$B$195,B51,$C$4:$C$195,C51),0) -> 0.20068992
A52: Apr | B52: Northeast | C52: Apparel | D52: 2156 | E52: 45.34 | F52: =D52*E52 -> 97753.04 | G52: 2363 | H52: 46.15 | I52: =G52*H52 -> 109052.45 | J52: =I52-F52 -> 11299.41 | K52: =IFERROR(J52/F52,0) -> 0.11559139 | L52: 4 | M52: E-Commerce | N52: =SUMIFS($I$4:$I$195,$B$4:$B$195,B52,$C$4:$C$195,C52,$L$4:$L$195,"<="&L52) -> 370181.12 | O52: =IFERROR(N52/SUMIFS($F$4:$F$195,$B$4:$B$195,B52,$C$4:$C$195,C52),0) -> 0.28889633
A53: Apr | B53: Northeast | C53: Home Goods | D53: 1294 | E53: 65.49 | F53: =D53*E53 -> 84744.06 | G53: 1362 | H53: 65.49 | I53: =G53*H53 -> 89197.38 | J53: =I53-F53 -> 4453.32 | K53: =IFERROR(J53/F53,0) -> 0.052550232 | L53: 4 | M53: E-Commerce | N53: =SUMIFS($I$4:$I$195,$B$4:$B$195,B53,$C$4:$C$195,C53,$L$4:$L$195,"<="&L53) -> 315180.99 | O53: =IFERROR(N53/SUMIFS($F$4:$F$195,$B$4:$B$195,B53,$C$4:$C$195,C53),0) -> 0.283813
A54: Apr | B54: Northeast | C54: Electronics | D54: 539 | E54: 221.65 | F54: =D54*E54 -> 119469.35 | G54: 531 | H54: 227.19 | I54: =G54*H54 -> 120637.89 | J54: =I54-F54 -> 1168.54 | K54: =IFERROR(J54/F54,0) -> 0.0097810861 | L54: 4 | M54: E-Commerce | N54: =SUMIFS($I$4:$I$195,$B$4:$B$195,B54,$C$4:$C$195,C54,$L$4:$L$195,"<="&L54) -> 459255.51 | O54: =IFERROR(N54/SUMIFS($F$4:$F$195,$B$4:$B$195,B54,$C$4:$C$195,C54),0) -> 0.29321787
A55: Apr | B55: Northeast | C55: Outdoor | D55: 862 | E55: 95.71 | F55: =D55*E55 -> 82502.02 | G55: 827 | H55: 94.1 | I55: =G55*H55 -> 77820.7 | J55: =I55-F55 -> -4681.32 | K55: =IFERROR(J55/F55,0) -> -0.056741883 | L55: 4 | M55: Retail Stores | N55: =SUMIFS($I$4:$I$195,$B$4:$B$195,B55,$C$4:$C$195,C55,$L$4:$L$195,"<="&L55) -> 289421.04 | O55: =IFERROR(N55/SUMIFS($F$4:$F$195,$B$4:$B$195,B55,$C$4:$C$195,C55),0) -> 0.2674741
A56: Apr | B56: Midwest | C56: Apparel | D56: 1725 | E56: 45.34 | F56: =D56*E56 -> 78211.5 | G56: 1761 | H56: 45.77 | I56: =G56*H56 -> 80600.97 | J56: =I56-F56 -> 2389.47 | K56: =IFERROR(J56/F56,0) -> 0.03055139 | L56: 4 | M56: Retail Stores | N56: =SUMIFS($I$4:$I$195,$B$4:$B$195,B56,$C$4:$C$195,C56,$L$4:$L$195,"<="&L56) -> 282692.02 | O56: =IFERROR(N56/SUMIFS($F$4:$F$195,$B$4:$B$195,B56,$C$4:$C$195,C56),0) -> 0.27577266
A57: Apr | B57: Midwest | C57: Home Goods | D57: 1035 | E57: 65.49 | F57: =D57*E57 -> 67782.15 | G57: 1088 | H57: 64.37 | I57: =G57*H57 -> 70034.56 | J57: =I57-F57 -> 2252.41 | K57: =IFERROR(J57/F57,0) -> 0.033230135 | L57: 4 | M57: Retail Stores | N57: =SUMIFS($I$4:$I$195,$B$4:$B$195,B57,$C$4:$C$195,C57,$L$4:$L$195,"<="&L57) -> 256340.4 | O57: =IFERROR(N57/SUMIFS($F$4:$F$195,$B$4:$B$195,B57,$C$4:$C$195,C57),0) -> 0.28853551
A58: Apr | B58: Midwest | C58: Electronics | D58: 431 | E58: 221.65 | F58: =D58*E58 -> 95531.15 | G58: 395 | H58: 220.88 | I58: =G58*H58 -> 87247.6 | J58: =I58-F58 -> -8283.55 | K58: =IFERROR(J58/F58,0) -> -0.08671046 | L58: 4 | M58: E-Commerce | N58: =SUMIFS($I$4:$I$195,$B$4:$B$195,B58,$C$4:$C$195,C58,$L$4:$L$195,"<="&L58) -> 357720.99 | O58: =IFERROR(N58/SUMIFS($F$4:$F$195,$B$4:$B$195,B58,$C$4:$C$195,C58),0) -> 0.28550989
... A86: Jun | B86: Northeast | C86: Electronics | D86: 578 | E86: 222.75 | F86: =D86*E86 -> 128749.5 | G86: 541 | H86: 225.48 | I86: =G86*H86 -> 121984.68 | J86: =I86-F86 -> -6764.82 | K86: =IFERROR(J86/F86,0) -> -0.052542495 | L86: 6 | M86: E-Commerce | N86: =SUMIFS($I$4:$I$195,$B$4:$B$195,B86,$C$4:$C$195,C86,$L$4:$L$195,"<="&L86) -> 691072.77 | O86: =IFERROR(N86/SUMIFS($F$4:$F$195,$B$4:$B$195,B86,$C$4:$C$195,C86),0) -> 0.44122472
A87: Jun | B87: Northeast | C87: Outdoor | D87: 924 | E87: 96.19 | F87: =D87*E87 -> 88879.56 | G87: 1013 | H87: 98.77 | I87: =G87*H87 -> 100054.01 | J87: =I87-F87 -> 11174.45 | K87: =IFERROR(J87/F87,0) -> 0.12572576 | L87: 6 | M87: Retail Stores | N87: =SUMIFS($I$4:$I$195,$B$4:$B$195,B87,$C$4:$C$195,C87,$L$4:$L$195,"<="&L87) -> 470290.21 | O87: =IFERROR(N87/SUMIFS($F$4:$F$195,$B$4:$B$195,B87,$C$4:$C$195,C87),0) -> 0.43462786 | P87: Promotional lift exceeded expectations for this line.
A88: Jun | B88: Midwest | C88: Apparel | D88: 1848 | E88: 45.56 | F88: =D88*E88 -> 84194.88 | G88: 2051 | H88: 46.92 | I88: =G88*H88 -> 96232.92 | J88: =I88-F88 -> 12038.04 | K88: =IFERROR(J88/F88,0) -> 0.14297829 | L88: 6 | M88: Retail Stores | N88: =SUMIFS($I$4:$I$195,$B$4:$B$195,B88,$C$4:$C$195,C88,$L$4:$L$195,"<="&L88) -> 467725.48 | O88: =IFERROR(N88/SUMIFS($F$4:$F$195,$B$4:$B$195,B88,$C$4:$C$195,C88),0) -> 0.45627712 | P88: Strong sell-through; consider raising next year's unit forecast.
A89: Jun | B89: Midwest | C89: Home Goods | D89: 1109 | E89: 65.81 | F89: =D89*E89 -> 72983.29 | G89: 1121 | H89: 64.93 | I89: =G89*H89 -> 72786.53 | J89: =I89-F89 -> -196.76 | K89: =IFERROR(J89/F89,0) -> -0.0026959596 | L89: 6 | M89: Retail Stores | N89: =SUMIFS($I$4:$I$195,$B$4:$B$195,B89,$C$4:$C$195,C89,$L$4:$L$195,"<="&L89) -> 392187.75 | O89: =IFERROR(N89/SUMIFS($F$4:$F$195,$B$4:$B$195,B89,$C$4:$C$195,C89),0) -> 0.44144463
A90: Jun | B90: Midwest | C90: Electronics | D90: 462 | E90: 222.75 | F90: =D90*E90 -> 102910.5 | G90: 427 | H90: 221.02 | I90: =G90*H90 -> 94375.54 | J90: =I90-F90 -> -8534.96 | K90: =IFERROR(J90/F90,0) -> -0.082935755 | L90: 6 | M90: Retail Stores | N90: =SUMIFS($I$4:$I$195,$B$4:$B$195,B90,$C$4:$C$195,C90,$L$4:$L$195,"<="&L90) -> 555712.7 | O90: =IFERROR(N90/SUMIFS($F$4:$F$195,$B$4:$B$195,B90,$C$4:$C$195,C90),0) -> 0.44353414
A91: Jun | B91: Midwest | C91: Outdoor | D91: 739 | E91: 96.19 | F91: =D91*E91 -> 71084.41 | G91: 737 | H91: 96.88 | I91: =G91*H91 -> 71400.56 | J91: =I91-F91 -> 316.15 | K91: =IFERROR(J91/F91,0) -> 0.0044475294 | L91: 6 | M91: Retail Stores | N91: =SUMIFS($I$4:$I$195,$B$4:$B$195,B91,$C$4:$C$195,C91,$L$4:$L$195,"<="&L91) -> 382548.09 | O91: =IFERROR(N91/SUMIFS($F$4:$F$195,$B$4:$B$195,B91,$C$4:$C$195,C91),0) -> 0.44197325
A92: Jun | B92: South | C92: Apparel | D92: 2100 | E92: 45.56 | F92: =D92*E92 -> 95676 | G92: 2324 | H92: 46.49 | I92: =G92*H92 -> 108042.76 | J92: =I92-F92 -> 12366.76 | K92: =IFERROR(J92/F92,0) -> 0.12925666 | L92: 6 | M92: E-Commerce | N92: =SUMIFS($I$4:$I$195,$B$4:$B$195,B92,$C$4:$C$195,C92,$L$4:$L$195,"<="&L92) -> 541976.02 | O92: =IFERROR(N92/SUMIFS($F$4:$F$195,$B$4:$B$195,B92,$C$4:$C$195,C92),0) -> 0.46526515 | P92: Promotional lift exceeded expectations for this line.
A93: Jun | B93: South | C93: Home Goods | D93: 1260 | E93: 65.81 | F93: =D93*E93 -> 82920.6 | G93: 1353 | H93: 65.48 | I93: =G93*H93 -> 88594.44 | J93: =I93-F93 -> 5673.84 | K93: =IFERROR(J93/F93,0) -> 0.068424975 | L93: 6 | M93: E-Commerce | N93: =SUMIFS($I$4:$I$195,$B$4:$B$195,B93,$C$4:$C$195,C93,$L$4:$L$195,"<="&L93) -> 435625.27 | O93: =IFERROR(N93/SUMIFS($F$4:$F$195,$B$4:$B$195,B93,$C$4:$C$195,C93),0) -> 0.43149715
A94: Jun | B94: South | C94: Electronics | D94: 525 | E94: 222.75 | F94: =D94*E94 -> 116943.75 | G94: 576 | H94: 219.79 | I94: =G94*H94 -> 126599.04 | J94: =I94-F94 -> 9655.29 | K94: =IFERROR(J94/F94,0) -> 0.08256354 | L94: 6 | M94: Retail Stores | N94: =SUMIFS($I$4:$I$195,$B$4:$B$195,B94,$C$4:$C$195,C94,$L$4:$L$195,"<="&L94) -> 636880.67 | O94: =IFERROR(N94/SUMIFS($F$4:$F$195,$B$4:$B$195,B94,$C$4:$C$195,C94),0) -> 0.44731865
A95: Jun | B95: South | C95: Outdoor | D95: 840 | E95: 96.19 | F95: =D95*E95 -> 80799.6 | G95: 782 | H95: 96.93 | I95: =G95*H95 -> 75799.26 | J95: =I95-F95 -> -5000.34 | K95: =IFERROR(J95/F95,0) -> -0.061885702 | L95: 6 | M95: Retail Stores | N95: =SUMIFS($I$4:$I$195,$B$4:$B$195,B95,$C$4:$C$195,C95,$L$4:$L$195,"<="&L95) -> 440737.59 | O95: =IFERROR(N95/SUMIFS($F$4:$F$195,$B$4:$B$195,B95,$C$4:$C$195,C95),0) -> 0.44804798
A96: Jun | B96: West | C96: Apparel | D96: 2478 | E96: 45.56 | F96: =D96*E96 -> 112897.68 | G96: 2555 | H96: 46.28 | I96: =G96*H96 -> 118245.4 | J96: =I96-F96 -> 5347.72 | K96: =IFERROR(J96/F96,0) -> 0.047367847 | L96: 6 | M96: Retail Stores | N96: =SUMIFS($I$4:$I$195,$B$4:$B$195,B96,$C$4:$C$195,C96,$L$4:$L$195,"<="&L96) -> 618253.3 | O96: =IFERROR(N96/SUMIFS($F$4:$F$195,$B$4:$B$195,B96,$C$4:$C$195,C96),0) -> 0.44978483
A97: Jun | B97: West | C97: Home Goods | D97: 1487 | E97: 65.81 | F97: =D97*E97 -> 97859.47 | G97: 1542 | H97: 65.36 | I97: =G97*H97 -> 100785.12 | J97: =I97-F97 -> 2925.65 | K97: =IFERROR(J97/F97,0) -> 0.029896442 | L97: 6 | M97: E-Commerce | N97: =SUMIFS($I$4:$I$195,$B$4:$B$195,B97,$C$4:$C$195,C97,$L$4:$L$195,"<="&L97) -> 540349.25 | O97: =IFERROR(N97/SUMIFS($F$4:$F$195,$B$4:$B$195,B97,$C$4:$C$195,C97),0) -> 0.45358354
A98: Jun | B98: West | C98: Electronics | D98: 620 | E98: 222.75 | F98: =D98*E98 -> 138105 | G98: 676 | H98: 227.72 | I98: =G98*H98 -> 153938.72 | J98: =I98-F98 -> 15833.72 | K98: =IFERROR(J98/F98,0) -> 0.11464987 | L98: 6 | M98: Retail Stores | N98: =SUMIFS($I$4:$I$195,$B$4:$B$195,B98,$C$4:$C$195,C98,$L$4:$L$195,"<="&L98) -> 754424.96 | O98: =IFERROR(N98/SUMIFS($F$4:$F$195,$B$4:$B$195,B98,$C$4:$C$195,C98),0) -> 0.44901947
A99: Jun | B99: West | C99: Outdoor | D99: 991 | E99: 96.19 | F99: =D99*E99 -> 95324.29 | G99: 986 | H99: 95.6 | I99: =G99*H99 -> 94261.6 | J99: =I99-F99 -> -1062.69 | K99: =IFERROR(J99/F99,0) -> -0.011148155 | L99: 6 | M99: Retail Stores | N99: =SUMIFS($I$4:$I$195,$B$4:$B$195,B99,$C$4:$C$195,C99,$L$4:$L$195,"<="&L99) -> 493178.74 | O99: =IFERROR(N99/SUMIFS($F$4:$F$195,$B$4:$B$195,B99,$C$4:$C$195,C99),0) -> 0.42488046
A100: Jul | B100: Northeast | C100: Apparel | D100: 2244 | E100: 45.67 | F100: =D100*E100 -> 102483.48 | G100: 2388 | H100: 46.21 | I100: =G100*H100 -> 110349.48 | J100: =I100-F100 -> 7866 | K100: =IFERROR(J100/F100,0) -> 0.076753834 | L100: 7 | M100: Retail Stores | N100: =SUMIFS($I$4:$I$195,$B$4:$B$195,B100,$C$4:$C$195,C100,$L$4:$L$195,"<="&L100) -> 682123.21 | O100: =IFERROR(N100/SUMIFS($F$4:$F$195,$B$4:$B$195,B100,$C$4:$C$195,C100),0) -> 0.53234183
A101: Jul | B101: Northeast | C101: Home Goods | D101: 1346 | E101: 65.97 | F101: =D101*E101 -> 88795.62 | G101: 1424 | H101: 66.47 | I101: =G101*H101 -> 94653.28 | J101: =I101-F101 -> 5857.66 | K101: =IFERROR(J101/F101,0) -> 0.065967893 | L101: 7 | M101: Retail Stores | N101: =SUMIFS($I$4:$I$195,$B$4:$B$195,B101,$C$4:$C$195,C101,$L$4:$L$195,"<="&L101) -> 586227.14 | O101: =IFERROR(N101/SUMIFS($F$4:$F$195,$B$4:$B$195,B101,$C$4:$C$195,C101),0) -> 0.52788362
A102: Jul | B102: Northeast | C102: Electronics | D102: 561 | E102: 223.3 | F102: =D102*E102 -> 125271.3 | G102: 512 | H102: 219.67 | I102: =G102*H102 -> 112471.04 | J102: =I102-F102 -> -12800.26 | K102: =IFERROR(J102/F102,0) -> -0.10218031 | L102: 7 | M102: Wholesale | N102: =SUMIFS($I$4:$I$195,$B$4:$B$195,B102,$C$4:$C$195,C102,$L$4:$L$195,"<="&L102) -> 803543.81 | O102: =IFERROR(N102/SUMIFS($F$4:$F$195,$B$4:$B$195,B102,$C$4:$C$195,C102),0) -> 0.51303338
A103: Jul | B103: Northeast | C103: Outdoor | D103: 898 | E103: 96.42 | F103: =D103*E103 -> 86585.16 | G103: 980 | H103: 97.12 | I103: =G103*H103 -> 95177.6 | J103: =I103-F103 -> 8592.44 | K103: =IFERROR(J103/F103,0) -> 0.099236867 | L103: 7 | M103: E-Commerce | N103: =SUMIFS($I$4:$I$195,$B$4:$B$195,B103,$C$4:$C$195,C103,$L$4:$L$195,"<="&L103) -> 565467.81 | O103: =IFERROR(N103/SUMIFS($F$4:$F$195,$B$4:$B$195,B103,$C$4:$C$195,C103),0) -> 0.5225881
A104: Jul | B104: Midwest | C104: Apparel | D104: 1795 | E104: 45.67 | F104: =D104*E104 -> 81977.65 | G104: 1843 | H104: 45.09 | I104: =G104*H104 -> 83100.87 | J104: =I104-F104 -> 1123.22 | K104: =IFERROR(J104/F104,0) -> 0.013701539 | L104: 7 | M104: Retail Stores | N104: =SUMIFS($I$4:$I$195,$B$4:$B$195,B104,$C$4:$C$195,C104,$L$4:$L$195,"<="&L104) -> 550826.35 | O104: =IFERROR(N104/SUMIFS($F$4:$F$195,$B$4:$B$195,B104,$C$4:$C$195,C104),0) -> 0.53734396
... A109: Jul | B109: South | C109: Home Goods | D109: 1224 | E109: 65.97 | F109: =D109*E109 -> 80747.28 | G109: 1152 | H109: 67.72 | I109: =G109*H109 -> 78013.44 | J109: =I109-F109 -> -2733.84 | K109: =IFERROR(J109/F109,0) -> -0.033856744 | L109: 7 | M109: Wholesale | N109: =SUMIFS($I$4:$I$195,$B$4:$B$195,B109,$C$4:$C$195,C109,$L$4:$L$195,"<="&L109) -> 513638.71 | O109: =IFERROR(N109/SUMIFS($F$4:$F$195,$B$4:$B$195,B109,$C$4:$C$195,C109),0) -> 0.50877132
A110: Jul | B110: South | C110: Electronics | D110: 510 | E110: 223.3 | F110: =D110*E110 -> 113883 | G110: 564 | H110: 227.89 | I110: =G110*H110 -> 128529.96 | J110: =I110-F110 -> 14646.96 | K110: =IFERROR(J110/F110,0) -> 0.1286141 | L110: 7 | M110: Wholesale | N110: =SUMIFS($I$4:$I$195,$B$4:$B$195,B110,$C$4:$C$195,C110,$L$4:$L$195,"<="&L110) -> 765410.63 | O110: =IFERROR(N110/SUMIFS($F$4:$F$195,$B$4:$B$195,B110,$C$4:$C$195,C110),0) -> 0.53759279 | P110: Strong sell-through; consider raising next year's unit forecast.
A111: Jul | B111: South | C111: Outdoor | D111: 816 | E111: 96.42 | F111: =D111*E111 -> 78678.72 | G111: 772 | H111: 98.95 | I111: =G111*H111 -> 76389.4 | J111: =I111-F111 -> -2289.32 | K111: =IFERROR(J111/F111,0) -> -0.029097067 | L111: 7 | M111: E-Commerce | N111: =SUMIFS($I$4:$I$195,$B$4:$B$195,B111,$C$4:$C$195,C111,$L$4:$L$195,"<="&L111) -> 517126.99 | O111: =IFERROR(N111/SUMIFS($F$4:$F$195,$B$4:$B$195,B111,$C$4:$C$195,C111),0) -> 0.52570443
A112: Jul | B112: West | C112: Apparel | D112: 2407 | E112: 45.67 | F112: =D112*E112 -> 109927.69 | G112: 2389 | H112: 46.29 | I112: =G112*H112 -> 110586.81 | J112: =I112-F112 -> 659.12 | K112: =IFERROR(J112/F112,0) -> 0.0059959415 | L112: 7 | M112: E-Commerce | N112: =SUMIFS($I$4:$I$195,$B$4:$B$195,B112,$C$4:$C$195,C112,$L$4:$L$195,"<="&L112) -> 728840.11 | O112: =IFERROR(N112/SUMIFS($F$4:$F$195,$B$4:$B$195,B112,$C$4:$C$195,C112),0) -> 0.53023772
A113: Jul | B113: West | C113: Home Goods | D113: 1444 | E113: 65.97 | F113: =D113*E113 -> 95260.68 | G113: 1386 | H113: 65.18 | I113: =G113*H113 -> 90339.48 | J113: =I113-F113 -> -4921.2 | K113: =IFERROR(J113/F113,0) -> -0.051660349 | L113: 7 | M113: E-Commerce | N113: =SUMIFS($I$4:$I$195,$B$4:$B$195,B113,$C$4:$C$195,C113,$L$4:$L$195,"<="&L113) -> 630688.73 | O113: =IFERROR(N113/SUMIFS($F$4:$F$195,$B$4:$B$195,B113,$C$4:$C$195,C113),0) -> 0.5294169
A114: Jul | B114: West | C114: Electronics | D114: 602 | E114: 223.3 | F114: =D114*E114 -> 134426.6 | G114: 594 | H114: 219.27 | I114: =G114*H114 -> 130246.38 | J114: =I114-F114 -> -4180.22 | K114: =IFERROR(J114/F114,0) -> -0.031096673 | L114: 7 | M114: E-Commerce | N114: =SUMIFS($I$4:$I$195,$B$4:$B$195,B114,$C$4:$C$195,C114,$L$4:$L$195,"<="&L114) -> 884671.34 | O114: =IFERROR(N114/SUMIFS($F$4:$F$195,$B$4:$B$195,B114,$C$4:$C$195,C114),0) -> 0.52653965
A115: Jul | B115: West | C115: Outdoor | D115: 963 | E115: 96.42 | F115: =D115*E115 -> 92852.46 | G115: 915 | H115: 98.92 | I115: =G115*H115 -> 90511.8 | J115: =I115-F115 -> -2340.66 | K115: =IFERROR(J115/F115,0) -> -0.025208379 | L115: 7 | M115: Retail Stores | N115: =SUMIFS($I$4:$I$195,$B$4:$B$195,B115,$C$4:$C$195,C115,$L$4:$L$195,"<="&L115) -> 583690.54 | O115: =IFERROR(N115/SUMIFS($F$4:$F$195,$B$4:$B$195,B115,$C$4:$C$195,C115),0) -> 0.50285765
A116: Aug | B116: Northeast | C116: Apparel | D116: 2332 | E116: 45.79 | F116: =D116*E116 -> 106782.28 | G116: 2505 | H116: 46.87 | I116: =G116*H116 -> 117409.35 | J116: =I116-F116 -> 10627.07 | K116: =IFERROR(J116/F116,0) -> 0.099520913 | L116: 8 | M116: Retail Stores | N116: =SUMIFS($I$4:$I$195,$B$4:$B$195,B116,$C$4:$C$195,C116,$L$4:$L$195,"<="&L116) -> 799532.56 | O116: =IFERROR(N116/SUMIFS($F$4:$F$195,$B$4:$B$195,B116,$C$4:$C$195,C116),0) -> 0.6239703
A117: Aug | B117: Northeast | C117: Home Goods | D117: 1399 | E117: 66.14 | F117: =D117*E117 -> 92529.86 | G117: 1458 | H117: 66.13 | I117: =G117*H117 -> 96417.54 | J117: =I117-F117 -> 3887.68 | K117: =IFERROR(J117/F117,0) -> 0.04201541 | L117: 8 | M117: Retail Stores | N117: =SUMIFS($I$4:$I$195,$B$4:$B$195,B117,$C$4:$C$195,C117,$L$4:$L$195,"<="&L117) -> 682644.68 | O117: =IFERROR(N117/SUMIFS($F$4:$F$195,$B$4:$B$195,B117,$C$4:$C$195,C117),0) -> 0.61470532
A118: Aug | B118: Northeast | C118: Electronics | D118: 583 | E118: 223.85 | F118: =D118*E118 -> 130504.55 | G118: 539 | H118: 228.03 | I118: =G118*H118 -> 122908.17 | J118: =I118-F118 -> -7596.38 | K118: =IFERROR(J118/F118,0) -> -0.058207779 | L118: 8 | M118: Retail Stores | N118: =SUMIFS($I$4:$I$195,$B$4:$B$195,B118,$C$4:$C$195,C118,$L$4:$L$195,"<="&L118) -> 926451.98 | O118: =IFERROR(N118/SUMIFS($F$4:$F$195,$B$4:$B$195,B118,$C$4:$C$195,C118),0) -> 0.59150575
A119: Aug | B119: Northeast | C119: Outdoor | D119: 933 | E119: 96.66 | F119: =D119*E119 -> 90183.78 | G119: 944 | H119: 98.01 | I119: =G119*H119 -> 92521.44 | J119: =I119-F119 -> 2337.66 | K119: =IFERROR(J119/F119,0) -> 0.025921069 | L119: 8 | M119: E-Commerce | N119: =SUMIFS($I$4:$I$195,$B$4:$B$195,B119,$C$4:$C$195,C119,$L$4:$L$195,"<="&L119) -> 657989.25 | O119: =IFERROR(N119/SUMIFS($F$4:$F$195,$B$4:$B$195,B119,$C$4:$C$195,C119),0) -> 0.60809359
A120: Aug | B120: Midwest | C120: Apparel | D120: 1866 | E120: 45.79 | F120: =D120*E120 -> 85444.14 | G120: 1822 | H120: 44.94 | I120: =G120*H120 -> 81880.68 | J120: =I120-F120 -> -3563.46 | K120: =IFERROR(J120/F120,0) -> -0.041705142 | L120: 8 | M120: Wholesale | N120: =SUMIFS($I$4:$I$195,$B$4:$B$195,B120,$C$4:$C$195,C120,$L$4:$L$195,"<="&L120) -> 632707.03 | O120: =IFERROR(N120/SUMIFS($F$4:$F$195,$B$4:$B$195,B120,$C$4:$C$195,C120),0) -> 0.61722047
A121: Aug | B121: Midwest | C121: Home Goods | D121: 1119 | E121: 66.14 | F121: =D121*E121 -> 74010.66 | G121: 1077 | H121: 66.74 | I121: =G121*H121 -> 71878.98 | J121: =I121-F121 -> -2131.68 | K121: =IFERROR(J121/F121,0) -> -0.028802337 | L121: 8 | M121: Wholesale | N121: =SUMIFS($I$4:$I$195,$B$4:$B$195,B121,$C$4:$C$195,C121,$L$4:$L$195,"<="&L121) -> 534797.25 | O121: =IFERROR(N121/SUMIFS($F$4:$F$195,$B$4:$B$195,B121,$C$4:$C$195,C121),0) -> 0.60196519
A122: Aug | B122: Midwest | C122: Electronics | D122: 466 | E122: 223.85 | F122: =D122*E122 -> 104314.1 | G122: 428 | H122: 226.05 | I122: =G122*H122 -> 96749.4 | J122: =I122-F122 -> -7564.7 | K122: =IFERROR(J122/F122,0) -> -0.07251848 | L122: 8 | M122: Retail Stores | N122: =SUMIFS($I$4:$I$195,$B$4:$B$195,B122,$C$4:$C$195,C122,$L$4:$L$195,"<="&L122) -> 763692.92 | O122: =IFERROR(N122/SUMIFS($F$4:$F$195,$B$4:$B$195,B122,$C$4:$C$195,C122),0) -> 0.60953057
... A127: Aug | B127: South | C127: Outdoor | D127: 848 | E127: 96.66 | F127: =D127*E127 -> 81967.68 | G127: 897 | H127: 95.68 | I127: =G127*H127 -> 85824.96 | J127: =I127-F127 -> 3857.28 | K127: =IFERROR(J127/F127,0) -> 0.047058548 | L127: 8 | M127: Retail Stores | N127: =SUMIFS($I$4:$I$195,$B$4:$B$195,B127,$C$4:$C$195,C127,$L$4:$L$195,"<="&L127) -> 602951.95 | O127: =IFERROR(N127/SUMIFS($F$4:$F$195,$B$4:$B$195,B127,$C$4:$C$195,C127),0) -> 0.61295294
A128: Aug | B128: West | C128: Apparel | D128: 2502 | E128: 45.79 | F128: =D128*E128 -> 114566.58 | G128: 2752 | H128: 46.98 | I128: =G128*H128 -> 129288.96 | J128: =I128-F128 -> 14722.38 | K128: =IFERROR(J128/F128,0) -> 0.12850501 | L128: 8 | M128: E-Commerce | N128: =SUMIFS($I$4:$I$195,$B$4:$B$195,B128,$C$4:$C$195,C128,$L$4:$L$195,"<="&L128) -> 858129.07 | O128: =IFERROR(N128/SUMIFS($F$4:$F$195,$B$4:$B$195,B128,$C$4:$C$195,C128),0) -> 0.6242966 | P128: Promotional lift exceeded expectations for this line.
A129: Aug | B129: West | C129: Home Goods | D129: 1501 | E129: 66.14 | F129: =D129*E129 -> 99276.14 | G129: 1620 | H129: 67.2 | I129: =G129*H129 -> 108864 | J129: =I129-F129 -> 9587.86 | K129: =IFERROR(J129/F129,0) -> 0.096577687 | L129: 8 | M129: Retail Stores | N129: =SUMIFS($I$4:$I$195,$B$4:$B$195,B129,$C$4:$C$195,C129,$L$4:$L$195,"<="&L129) -> 739552.73 | O129: =IFERROR(N129/SUMIFS($F$4:$F$195,$B$4:$B$195,B129,$C$4:$C$195,C129),0) -> 0.62080024
A130: Aug | B130: West | C130: Electronics | D130: 625 | E130: 223.85 | F130: =D130*E130 -> 139906.25 | G130: 607 | H130: 223.94 | I130: =G130*H130 -> 135931.58 | J130: =I130-F130 -> -3974.67 | K130: =IFERROR(J130/F130,0) -> -0.028409524 | L130: 8 | M130: Retail Stores | N130: =SUMIFS($I$4:$I$195,$B$4:$B$195,B130,$C$4:$C$195,C130,$L$4:$L$195,"<="&L130) -> 1020602.9 | O130: =IFERROR(N130/SUMIFS($F$4:$F$195,$B$4:$B$195,B130,$C$4:$C$195,C130),0) -> 0.60744356
A131: Aug | B131: West | C131: Outdoor | D131: 1001 | E131: 96.66 | F131: =D131*E131 -> 96756.66 | G131: 970 | H131: 95.34 | I131: =G131*H131 -> 92479.8 | J131: =I131-F131 -> -4276.86 | K131: =IFERROR(J131/F131,0) -> -0.044202229 | L131: 8 | M131: Retail Stores | N131: =SUMIFS($I$4:$I$195,$B$4:$B$195,B131,$C$4:$C$195,C131,$L$4:$L$195,"<="&L131) -> 676170.34 | O131: =IFERROR(N131/SUMIFS($F$4:$F$195,$B$4:$B$195,B131,$C$4:$C$195,C131),0) -> 0.58253031
A132: Sep | B132: Northeast | C132: Apparel | D132: 2200 | E132: 45.9 | F132: =D132*E132 -> 100980 | G132: 2416 | H132: 46.54 | I132: =G132*H132 -> 112440.64 | J132: =I132-F132 -> 11460.64 | K132: =IFERROR(J132/F132,0) -> 0.11349416 | L132: 9 | M132: Wholesale | N132: =SUMIFS($I$4:$I$195,$B$4:$B$195,B132,$C$4:$C$195,C132,$L$4:$L$195,"<="&L132) -> 911973.2 | O132: =IFERROR(N132/SUMIFS($F$4:$F$195,$B$4:$B$195,B132,$C$4:$C$195,C132),0) -> 0.7117211
A133: Sep | B133: Northeast | C133: Home Goods | D133: 1320 | E133: 66.3 | F133: =D133*E133 -> 87516 | G133: 1364 | H133: 65.97 | I133: =G133*H133 -> 89983.08 | J133: =I133-F133 -> 2467.08 | K133: =IFERROR(J133/F133,0) -> 0.028190045 | L133: 9 | M133: E-Commerce | N133: =SUMIFS($I$4:$I$195,$B$4:$B$195,B133,$C$4:$C$195,C133,$L$4:$L$195,"<="&L133) -> 772627.76 | O133: =IFERROR(N133/SUMIFS($F$4:$F$195,$B$4:$B$195,B133,$C$4:$C$195,C133),0) -> 0.69573295
A134: Sep | B134: Northeast | C134: Electronics | D134: 550 | E134: 224.4 | F134: =D134*E134 -> 123420 | G134: 501 | H134: 223.13 | I134: =G134*H134 -> 111788.13 | J134: =I134-F134 -> -11631.87 | K134: =IFERROR(J134/F134,0) -> -0.094246232 | L134: 9 | M134: Retail Stores | N134: =SUMIFS($I$4:$I$195,$B$4:$B$195,B134,$C$4:$C$195,C134,$L$4:$L$195,"<="&L134) -> 1038240.1 | O134: =IFERROR(N134/SUMIFS($F$4:$F$195,$B$4:$B$195,B134,$C$4:$C$195,C134),0) -> 0.66287839
A135: Sep | B135: Northeast | C135: Outdoor | D135: 880 | E135: 96.9 | F135: =D135*E135 -> 85272 | G135: 903 | H135: 98.13 | I135: =G135*H135 -> 88611.39 | J135: =I135-F135 -> 3339.39 | K135: =IFERROR(J135/F135,0) -> 0.039161624 | L135: 9 | M135: E-Commerce | N135: =SUMIFS($I$4:$I$195,$B$4:$B$195,B135,$C$4:$C$195,C135,$L$4:$L$195,"<="&L135) -> 746600.64 | O135: =IFERROR(N135/SUMIFS($F$4:$F$195,$B$4:$B$195,B135,$C$4:$C$195,C135),0) -> 0.68998553
A136: Sep | B136: Midwest | C136: Apparel | D136: 1760 | E136: 45.9 | F136: =D136*E136 -> 80784 | G136: 1757 | H136: 45.47 | I136: =G136*H136 -> 79890.79 | J136: =I136-F136 -> -893.21 | K136: =IFERROR(J136/F136,0) -> -0.011056769 | L136: 9 | M136: E-Commerce | N136: =SUMIFS($I$4:$I$195,$B$4:$B$195,B136,$C$4:$C$195,C136,$L$4:$L$195,"<="&L136) -> 712597.82 | O136: =IFERROR(N136/SUMIFS($F$4:$F$195,$B$4:$B$195,B136,$C$4:$C$195,C136),0) -> 0.6951558
A137: Sep | B137: Midwest | C137: Home Goods | D137: 1056 | E137: 66.3 | F137: =D137*E137 -> 70012.8 | G137: 1151 | H137: 67.61 | I137: =G137*H137 -> 77819.11 | J137: =I137-F137 -> 7806.31 | K137: =IFERROR(J137/F137,0) -> 0.11149833 | L137: 9 | M137: Retail Stores | N137: =SUMIFS($I$4:$I$195,$B$4:$B$195,B137,$C$4:$C$195,C137,$L$4:$L$195,"<="&L137) -> 612616.36 | O137: =IFERROR(N137/SUMIFS($F$4:$F$195,$B$4:$B$195,B137,$C$4:$C$195,C137),0) -> 0.689558
A138: Sep | B138: Midwest | C138: Electronics | D138: 440 | E138: 224.4 | F138: =D138*E138 -> 98736 | G138: 408 | H138: 225.7 | I138: =G138*H138 -> 92085.6 | J138: =I138-F138 -> -6650.4 | K138: =IFERROR(J138/F138,0) -> -0.067355372 | L138: 9 | M138: E-Commerce | N138: =SUMIFS($I$4:$I$195,$B$4:$B$195,B138,$C$4:$C$195,C138,$L$4:$L$195,"<="&L138) -> 855778.52 | O138: =IFERROR(N138/SUMIFS($F$4:$F$195,$B$4:$B$195,B138,$C$4:$C$195,C138),0) -> 0.68302737
A139: Sep | B139: Midwest | C139: Outdoor | D139: 704 | E139: 96.9 | F139: =D139*E139 -> 68217.6 | G139: 688 | H139: 98.93 | I139: =G139*H139 -> 68063.84 | J139: =I139-F139 -> -153.76 | K139: =IFERROR(J139/F139,0) -> -0.0022539638 | L139: 9 | M139: E-Commerce | N139: =SUMIFS($I$4:$I$195,$B$4:$B$195,B139,$C$4:$C$195,C139,$L$4:$L$195,"<="&L139) -> 593144.68 | O139: =IFERROR(N139/SUMIFS($F$4:$F$195,$B$4:$B$195,B139,$C$4:$C$195,C139),0) -> 0.685284
A140: Sep | B140: South | C140: Apparel | D140: 2000 | E140: 45.9 | F140: =D140*E140 -> 91800 | G140: 2089 | H140: 45.5 | I140: =G140*H140 -> 95049.5 | J140: =I140-F140 -> 3249.5 | K140: =IFERROR(J140/F140,0) -> 0.035397603 | L140: 9 | M140: Retail Stores | N140: =SUMIFS($I$4:$I$195,$B$4:$B$195,B140,$C$4:$C$195,C140,$L$4:$L$195,"<="&L140) -> 831125.62 | O140: =IFERROR(N140/SUMIFS($F$4:$F$195,$B$4:$B$195,B140,$C$4:$C$195,C140),0) -> 0.71348874
... A195: Dec | B195: West | C195: Outdoor | D195: 1463 | E195: 97.61 | F195: =D195*E195 -> 142803.43 | G195: 1473 | H195: 97.78 | I195: =G195*H195 -> 144029.94 | J195: =I195-F195 -> 1226.51 | K195: =IFERROR(J195/F195,0) -> 0.0085887993 | L195: 12 | M195: E-Commerce | N195: =SUMIFS($I$4:$I$195,$B$4:$B$195,B195,$C$4:$C$195,C195,$L$4:$L$195,"<="&L195) -> 1132542.4 | O195: =IFERROR(N195/SUMIFS($F$4:$F$195,$B$4:$B$195,B195,$C$4:$C$195,C195),0) -> 0.9757013
A196: TOTAL | D196: =SUM(D4:D195) -> 238680 | E196: =AVERAGE(E4:E195) -> 107.71 | F196: =SUM(F4:F195) -> 19060826 | G196: =SUM(G4:G195) -> 241874 | H196: =AVERAGE(H4:H195) -> 108.23078 | I196: =SUM(I4:I195) -> 19368646 | J196: =SUM(J4:J195) -> 307819.98 | K196: =IFERROR(J196/F196,0) -> 0.016149351 | N196: =I196 -> 19368646 | O196: =IFERROR(N196/F196,0) -> 1.0161494

Sheet Expense Detail
A1: Expense Detail — FY2027 Budget vs. Actual (by Month, Department)
A3: Month | B3: Department | C3: Budgeted Amount | D3: Actual Amount | E3: Variance $ | F3: Variance % | G3: Expense Category | H3: Cost Center Code | I3: Month # | J3: YTD Actual Amount | K3: % of Annual Budget Used | L3: Notes
A4: Jan | B4: Sales | C4: 180000 | D4: 173595 | E4: =D4-C4 -> -6405 | F4: =IFERROR(E4/C4,0) -> -0.035583333 | G4: Payroll | H4: CC-1000 | I4: 1 | J4: =SUMIFS($D$4:$D$99,$B$4:$B$99,B4,$I$4:$I$99,"<="&I4) -> 173595 | K4: =IFERROR(J4/SUMIFS($C$4:$C$99,$B$4:$B$99,B4),0) -> 0.079192054
A5: Jan | B5: Marketing | C5: 150000 | D5: 165662 | E5: =D5-C5 -> 15662 | F5: =IFERROR(E5/C5,0) -> 0.10441333 | G5: Marketing Spend | H5: CC-2000 | I5: 1 | J5: =SUMIFS($D$4:$D$99,$B$4:$B$99,B5,$I$4:$I$99,"<="&I5) -> 165662 | K5: =IFERROR(J5/SUMIFS($C$4:$C$99,$B$4:$B$99,B5),0) -> 0.084282471 | L5: Overspend driven by higher contractor/vendor usage this month.
A6: Jan | B6: Operations | C6: 241120 | D6: 233149 | E6: =D6-C6 -> -7971 | F6: =IFERROR(E6/C6,0) -> -0.033058228 | G6: Payroll | H6: CC-3000 | I6: 1 | J6: =SUMIFS($D$4:$D$99,$B$4:$B$99,B6,$I$4:$I$99,"<="&I6) -> 233149 | K6: =IFERROR(J6/SUMIFS($C$4:$C$99,$B$4:$B$99,B6),0) -> 0.07442646
A7: Jan | B7: IT | C7: 95000 | D7: 95778 | E7: =D7-C7 -> 778 | F7: =IFERROR(E7/C7,0) -> 0.0081894737 | G7: Software & IT | H7: CC-4400 | I7: 1 | J7: =SUMIFS($D$4:$D$99,$B$4:$B$99,B7,$I$4:$I$99,"<="&I7) -> 95778 | K7: =IFERROR(J7/SUMIFS($C$4:$C$99,$B$4:$B$99,B7),0) -> 0.082786483
A8: Jan | B8: HR | C8: 60000 | D8: 64807 | E8: =D8-C8 -> 4807 | F8: =IFERROR(E8/C8,0) -> 0.080116667 | G8: Payroll | H8: CC-5000 | I8: 1 | J8: =SUMIFS($D$4:$D$99,$B$4:$B$99,B8,$I$4:$I$99,"<="&I8) -> 64807 | K8: =IFERROR(J8/SUMIFS($C$4:$C$99,$B$4:$B$99,B8),0) -> 0.088692637
A9: Jan | B9: Finance | C9: 70000 | D9: 72573 | E9: =D9-C9 -> 2573 | F9: =IFERROR(E9/C9,0) -> 0.036757143 | G9: Professional Services | H9: CC-6000 | I9: 1 | J9: =SUMIFS($D$4:$D$99,$B$4:$B$99,B9,$I$4:$I$99,"<="&I9) -> 72573 | K9: =IFERROR(J9/SUMIFS($C$4:$C$99,$B$4:$B$99,B9),0) -> 0.085132215
A10: Jan | B10: Customer Service | C10: 102000 | D10: 108157 | E10: =D10-C10 -> 6157 | F10: =IFERROR(E10/C10,0) -> 0.060362745 | G10: Payroll | H10: CC-7000 | I10: 1 | J10: =SUMIFS($D$4:$D$99,$B$4:$B$99,B10,$I$4:$I$99,"<="&I10) -> 108157 | K10: =IFERROR(J10/SUMIFS($C$4:$C$99,$B$4:$B$99,B10),0) -> 0.0994903
A11: Jan | B11: Executive | C11: 110000 | D11: 107881 | E11: =D11-C11 -> -2119 | F11: =IFERROR(E11/C11,0) -> -0.019263636 | G11: Payroll | H11: CC-8000 | I11: 1 | J11: =SUMIFS($D$4:$D$99,$B$4:$B$99,B11,$I$4:$I$99,"<="&I11) -> 107881 | K11: =IFERROR(J11/SUMIFS($C$4:$C$99,$B$4:$B$99,B11),0) -> 0.080532128
A12: Feb | B12: Sales | C12: 180486 | D12: 183849 | E12: =D12-C12 -> 3363 | F12: =IFERROR(E12/C12,0) -> 0.018633024 | G12: Payroll | H12: CC-1000 | I12: 2 | J12: =SUMIFS($D$4:$D$99,$B$4:$B$99,B12,$I$4:$I$99,"<="&I12) -> 357444 | K12: =IFERROR(J12/SUMIFS($C$4:$C$99,$B$4:$B$99,B12),0) -> 0.16306186
A13: Feb | B13: Marketing | C13: 150405 | D13: 147097 | E13: =D13-C13 -> -3308 | F13: =IFERROR(E13/C13,0) -> -0.02199395 | G13: Marketing Spend | H13: CC-2000 | I13: 2 | J13: =SUMIFS($D$4:$D$99,$B$4:$B$99,B13,$I$4:$I$99,"<="&I13) -> 312759 | K13: =IFERROR(J13/SUMIFS($C$4:$C$99,$B$4:$B$99,B13),0) -> 0.15911978
A14: Feb | B14: Operations | C14: 243095 | D14: 247231 | E14: =D14-C14 -> 4136 | F14: =IFERROR(E14/C14,0) -> 0.017013925 | G14: Payroll | H14: CC-3000 | I14: 2 | J14: =SUMIFS($D$4:$D$99,$B$4:$B$99,B14,$I$4:$I$99,"<="&I14) -> 480380 | K14: =IFERROR(J14/SUMIFS($C$4:$C$99,$B$4:$B$99,B14),0) -> 0.15334822
A15: Feb | B15: IT | C15: 95256 | D15: 93842 | E15: =D15-C15 -> -1414 | F15: =IFERROR(E15/C15,0) -> -0.014844209 | G15: Software & IT | H15: CC-4400 | I15: 2 | J15: =SUMIFS($D$4:$D$99,$B$4:$B$99,B15,$I$4:$I$99,"<="&I15) -> 189620 | K15: =IFERROR(J15/SUMIFS($C$4:$C$99,$B$4:$B$99,B15),0) -> 0.16389957
A16: Feb | B16: HR | C16: 60162 | D16: 57876 | E16: =D16-C16 -> -2286 | F16: =IFERROR(E16/C16,0) -> -0.037997407 | G16: Payroll | H16: CC-5000 | I16: 2 | J16: =SUMIFS($D$4:$D$99,$B$4:$B$99,B16,$I$4:$I$99,"<="&I16) -> 122683 | K16: =IFERROR(J16/SUMIFS($C$4:$C$99,$B$4:$B$99,B16),0) -> 0.16789974
A17: Feb | B17: Finance | C17: 70189 | D17: 67881 | E17: =D17-C17 -> -2308 | F17: =IFERROR(E17/C17,0) -> -0.032882645 | G17: Professional Services | H17: CC-6000 | I17: 2 | J17: =SUMIFS($D$4:$D$99,$B$4:$B$99,B17,$I$4:$I$99,"<="&I17) -> 140454 | K17: =IFERROR(J17/SUMIFS($C$4:$C$99,$B$4:$B$99,B17),0) -> 0.16476045
A18: Feb | B18: Customer Service | C18: 85230 | D18: 88901 | E18: =D18-C18 -> 3671 | F18: =IFERROR(E18/C18,0) -> 0.043071688 | G18: Payroll | H18: CC-7000 | I18: 2 | J18: =SUMIFS($D$4:$D$99,$B$4:$B$99,B18,$I$4:$I$99,"<="&I18) -> 197058 | K18: =IFERROR(J18/SUMIFS($C$4:$C$99,$B$4:$B$99,B18),0) -> 0.1812676
A19: Feb | B19: Executive | C19: 110297 | D19: 122565 | E19: =D19-C19 -> 12268 | F19: =IFERROR(E19/C19,0) -> 0.11122696 | G19: Payroll | H19: CC-8000 | I19: 2 | J19: =SUMIFS($D$4:$D$99,$B$4:$B$99,B19,$I$4:$I$99,"<="&I19) -> 230446 | K19: =IFERROR(J19/SUMIFS($C$4:$C$99,$B$4:$B$99,B19),0) -> 0.17202572 | L19: One-time expense pulled forward from a later month.
A20: Mar | B20: Sales | C20: 180972 | D20: 163316 | E20: =D20-C20 -> -17656 | F20: =IFERROR(E20/C20,0) -> -0.097562054 | G20: Payroll | H20: CC-1000 | I20: 3 | J20: =SUMIFS($D$4:$D$99,$B$4:$B$99,B20,$I$4:$I$99,"<="&I20) -> 520760 | K20: =IFERROR(J20/SUMIFS($C$4:$C$99,$B$4:$B$99,B20),0) -> 0.23756476
A21: Mar | B21: Marketing | C21: 150810 | D21: 170044 | E21: =D21-C21 -> 19234 | F21: =IFERROR(E21/C21,0) -> 0.12753796 | G21: Marketing Spend | H21: CC-2000 | I21: 3 | J21: =SUMIFS($D$4:$D$99,$B$4:$B$99,B21,$I$4:$I$99,"<="&I21) -> 482803 | K21: =IFERROR(J21/SUMIFS($C$4:$C$99,$B$4:$B$99,B21),0) -> 0.24563165 | L21: Overspend driven by higher contractor/vendor usage this month.
A22: Mar | B22: Operations | C22: 249721 | D22: 239214 | E22: =D22-C22 -> -10507 | F22: =IFERROR(E22/C22,0) -> -0.042074956 | G22: Payroll | H22: CC-3000 | I22: 3 | J22: =SUMIFS($D$4:$D$99,$B$4:$B$99,B22,$I$4:$I$99,"<="&I22) -> 719594 | K22: =IFERROR(J22/SUMIFS($C$4:$C$99,$B$4:$B$99,B22),0) -> 0.22971076
A23: Mar | B23: IT | C23: 95513 | D23: 95278 | E23: =D23-C23 -> -235 | F23: =IFERROR(E23/C23,0) -> -0.0024603981 | G23: Software & IT | H23: CC-4400 | I23: 3 | J23: =SUMIFS($D$4:$D$99,$B$4:$B$99,B23,$I$4:$I$99,"<="&I23) -> 284898 | K23: =IFERROR(J23/SUMIFS($C$4:$C$99,$B$4:$B$99,B23),0) -> 0.24625387
A24: Mar | B24: HR | C24: 60324 | D24: 62329 | E24: =D24-C24 -> 2005 | F24: =IFERROR(E24/C24,0) -> 0.033237186 | G24: Payroll | H24: CC-5000 | I24: 3 | J24: =SUMIFS($D$4:$D$99,$B$4:$B$99,B24,$I$4:$I$99,"<="&I24) -> 185012 | K24: =IFERROR(J24/SUMIFS($C$4:$C$99,$B$4:$B$99,B24),0) -> 0.25320108
A25: Mar | B25: Finance | C25: 70378 | D25: 67399 | E25: =D25-C25 -> -2979 | F25: =IFERROR(E25/C25,0) -> -0.042328569 | G25: Professional Services | H25: CC-6000 | I25: 3 | J25: =SUMIFS($D$4:$D$99,$B$4:$B$99,B25,$I$4:$I$99,"<="&I25) -> 207853 | K25: =IFERROR(J25/SUMIFS($C$4:$C$99,$B$4:$B$99,B25),0) -> 0.24382327
A26: Mar | B26: Customer Service | C26: 85459 | D26: 86678 | E26: =D26-C26 -> 1219 | F26: =IFERROR(E26/C26,0) -> 0.01426415 | G26: Payroll | H26: CC-7000 | I26: 3 | J26: =SUMIFS($D$4:$D$99,$B$4:$B$99,B26,$I$4:$I$99,"<="&I26) -> 283736 | K26: =IFERROR(J26/SUMIFS($C$4:$C$99,$B$4:$B$99,B26),0) -> 0.26100003
A27: Mar | B27: Executive | C27: 110594 | D27: 118429 | E27: =D27-C27 -> 7835 | F27: =IFERROR(E27/C27,0) -> 0.070844711 | G27: Payroll | H27: CC-8000 | I27: 3 | J27: =SUMIFS($D$4:$D$99,$B$4:$B$99,B27,$I$4:$I$99,"<="&I27) -> 348875 | K27: =IFERROR(J27/SUMIFS($C$4:$C$99,$B$4:$B$99,B27),0) -> 0.26043183
A28: Apr | B28: Sales | C28: 181458 | D28: 182830 | E28: =D28-C28 -> 1372 | F28: =IFERROR(E28/C28,0) -> 0.0075609783 | G28: Payroll | H28: CC-1000 | I28: 4 | J28: =SUMIFS($D$4:$D$99,$B$4:$B$99,B28,$I$4:$I$99,"<="&I28) -> 703590 | K28: =IFERROR(J28/SUMIFS($C$4:$C$99,$B$4:$B$99,B28),0) -> 0.32096971
A29: Apr | B29: Marketing | C29: 151215 | D29: 136719 | E29: =D29-C29 -> -14496 | F29: =IFERROR(E29/C29,0) -> -0.095863506 | G29: Marketing Spend | H29: CC-2000 | I29: 4 | J29: =SUMIFS($D$4:$D$99,$B$4:$B$99,B29,$I$4:$I$99,"<="&I29) -> 619522 | K29: =IFERROR(J29/SUMIFS($C$4:$C$99,$B$4:$B$99,B29),0) -> 0.31518903
A30: Apr | B30: Operations | C30: 253719 | D30: 246264 | E30: =D30-C30 -> -7455 | F30: =IFERROR(E30/C30,0) -> -0.0293829 | G30: Payroll | H30: CC-3000 | I30: 4 | J30: =SUMIFS($D$4:$D$99,$B$4:$B$99,B30,$I$4:$I$99,"<="&I30) -> 965858 | K30: =IFERROR(J30/SUMIFS($C$4:$C$99,$B$4:$B$99,B30),0) -> 0.30832383
A31: Apr | B31: IT | C31: 95770 | D31: 95488 | E31: =D31-C31 -> -282 | F31: =IFERROR(E31/C31,0) -> -0.0029445547 | G31: Software & IT | H31: CC-4400 | I31: 4 | J31: =SUMIFS($D$4:$D$99,$B$4:$B$99,B31,$I$4:$I$99,"<="&I31) -> 380386 | K31: =IFERROR(J31/SUMIFS($C$4:$C$99,$B$4:$B$99,B31),0) -> 0.32878969
A32: Apr | B32: HR | C32: 60486 | D32: 57969 | E32: =D32-C32 -> -2517 | F32: =IFERROR(E32/C32,0) -> -0.041612935 | G32: Payroll | H32: CC-5000 | I32: 4 | J32: =SUMIFS($D$4:$D$99,$B$4:$B$99,B32,$I$4:$I$99,"<="&I32) -> 242981 | K32: =IFERROR(J32/SUMIFS($C$4:$C$99,$B$4:$B$99,B32),0) -> 0.33253546
A33: Apr | B33: Finance | C33: 70567 | D33: 74755 | E33: =D33-C33 -> 4188 | F33: =IFERROR(E33/C33,0) -> 0.059347854 | G33: Professional Services | H33: CC-6000 | I33: 4 | J33: =SUMIFS($D$4:$D$99,$B$4:$B$99,B33,$I$4:$I$99,"<="&I33) -> 282608 | K33: =IFERROR(J33/SUMIFS($C$4:$C$99,$B$4:$B$99,B33),0) -> 0.3315151
... A36: May | B36: Sales | C36: 181944 | D36: 178760 | E36: =D36-C36 -> -3184 | F36: =IFERROR(E36/C36,0) -> -0.01749989 | G36: Payroll | H36: CC-1000 | I36: 5 | J36: =SUMIFS($D$4:$D$99,$B$4:$B$99,B36,$I$4:$I$99,"<="&I36) -> 882350 | K36: =IFERROR(J36/SUMIFS($C$4:$C$99,$B$4:$B$99,B36),0) -> 0.40251798
A37: May | B37: Marketing | C37: 151620 | D37: 172724 | E37: =D37-C37 -> 21104 | F37: =IFERROR(E37/C37,0) -> 0.13919008 | G37: Marketing Spend | H37: CC-2000 | I37: 5 | J37: =SUMIFS($D$4:$D$99,$B$4:$B$99,B37,$I$4:$I$99,"<="&I37) -> 792246 | K37: =IFERROR(J37/SUMIFS($C$4:$C$99,$B$4:$B$99,B37),0) -> 0.40306437 | L37: One-time expense pulled forward from a later month.
A38: May | B38: Operations | C38: 255732 | D38: 250461 | E38: =D38-C38 -> -5271 | F38: =IFERROR(E38/C38,0) -> -0.020611421 | G38: Payroll | H38: CC-3000 | I38: 5 | J38: =SUMIFS($D$4:$D$99,$B$4:$B$99,B38,$I$4:$I$99,"<="&I38) -> 1216319 | K38: =IFERROR(J38/SUMIFS($C$4:$C$99,$B$4:$B$99,B38),0) -> 0.38827667
A39: May | B39: IT | C39: 96026 | D39: 102622 | E39: =D39-C39 -> 6596 | F39: =IFERROR(E39/C39,0) -> 0.06868973 | G39: Software & IT | H39: CC-4400 | I39: 5 | J39: =SUMIFS($D$4:$D$99,$B$4:$B$99,B39,$I$4:$I$99,"<="&I39) -> 483008 | K39: =IFERROR(J39/SUMIFS($C$4:$C$99,$B$4:$B$99,B39),0) -> 0.41749184
A40: May | B40: HR | C40: 60648 | D40: 58527 | E40: =D40-C40 -> -2121 | F40: =IFERROR(E40/C40,0) -> -0.034972299 | G40: Payroll | H40: CC-5000 | I40: 5 | J40: =SUMIFS($D$4:$D$99,$B$4:$B$99,B40,$I$4:$I$99,"<="&I40) -> 301508 | K40: =IFERROR(J40/SUMIFS($C$4:$C$99,$B$4:$B$99,B40),0) -> 0.4126335
A41: May | B41: Finance | C41: 70756 | D41: 67950 | E41: =D41-C41 -> -2806 | F41: =IFERROR(E41/C41,0) -> -0.039657414 | G41: Professional Services | H41: CC-6000 | I41: 5 | J41: =SUMIFS($D$4:$D$99,$B$4:$B$99,B41,$I$4:$I$99,"<="&I41) -> 350558 | K41: =IFERROR(J41/SUMIFS($C$4:$C$99,$B$4:$B$99,B41),0) -> 0.41122427
A42: May | B42: Customer Service | C42: 85918 | D42: 79814 | E42: =D42-C42 -> -6104 | F42: =IFERROR(E42/C42,0) -> -0.071044484 | G42: Payroll | H42: CC-7000 | I42: 5 | J42: =SUMIFS($D$4:$D$99,$B$4:$B$99,B42,$I$4:$I$99,"<="&I42) -> 448258 | K42: =IFERROR(J42/SUMIFS($C$4:$C$99,$B$4:$B$99,B42),0) -> 0.41233876
A43: May | B43: Executive | C43: 111188 | D43: 105208 | E43: =D43-C43 -> -5980 | F43: =IFERROR(E43/C43,0) -> -0.053782782 | G43: Payroll | H43: CC-8000 | I43: 5 | J43: =SUMIFS($D$4:$D$99,$B$4:$B$99,B43,$I$4:$I$99,"<="&I43) -> 568615 | K43: =IFERROR(J43/SUMIFS($C$4:$C$99,$B$4:$B$99,B43),0) -> 0.42446562
A44: Jun | B44: Sales | C44: 182430 | D44: 169421 | E44: =D44-C44 -> -13009 | F44: =IFERROR(E44/C44,0) -> -0.071309543 | G44: Payroll | H44: CC-1000 | I44: 6 | J44: =SUMIFS($D$4:$D$99,$B$4:$B$99,B44,$I$4:$I$99,"<="&I44) -> 1051771 | K44: =IFERROR(J44/SUMIFS($C$4:$C$99,$B$4:$B$99,B44),0) -> 0.4798059
A45: Jun | B45: Marketing | C45: 152025 | D45: 156374 | E45: =D45-C45 -> 4349 | F45: =IFERROR(E45/C45,0) -> 0.028607137 | G45: Marketing Spend | H45: CC-2000 | I45: 6 | J45: =SUMIFS($D$4:$D$99,$B$4:$B$99,B45,$I$4:$I$99,"<="&I45) -> 948620 | K45: =IFERROR(J45/SUMIFS($C$4:$C$99,$B$4:$B$99,B45),0) -> 0.48262147
A46: Jun | B46: Operations | C46: 259760 | D46: 281301 | E46: =D46-C46 -> 21541 | F46: =IFERROR(E46/C46,0) -> 0.082926548 | G46: Payroll | H46: CC-3000 | I46: 6 | J46: =SUMIFS($D$4:$D$99,$B$4:$B$99,B46,$I$4:$I$99,"<="&I46) -> 1497620 | K46: =IFERROR(J46/SUMIFS($C$4:$C$99,$B$4:$B$99,B46),0) -> 0.47807435
A47: Jun | B47: IT | C47: 96282 | D47: 90932 | E47: =D47-C47 -> -5350 | F47: =IFERROR(E47/C47,0) -> -0.055565942 | G47: Software & IT | H47: CC-4400 | I47: 6 | J47: =SUMIFS($D$4:$D$99,$B$4:$B$99,B47,$I$4:$I$99,"<="&I47) -> 573940 | K47: =IFERROR(J47/SUMIFS($C$4:$C$99,$B$4:$B$99,B47),0) -> 0.49608964
A48: Jun | B48: HR | C48: 60810 | D48: 57887 | E48: =D48-C48 -> -2923 | F48: =IFERROR(E48/C48,0) -> -0.048067752 | G48: Payroll | H48: CC-5000 | I48: 6 | J48: =SUMIFS($D$4:$D$99,$B$4:$B$99,B48,$I$4:$I$99,"<="&I48) -> 359395 | K48: =IFERROR(J48/SUMIFS($C$4:$C$99,$B$4:$B$99,B48),0) -> 0.49185567
A49: Jun | B49: Finance | C49: 70945 | D49: 72095 | E49: =D49-C49 -> 1150 | F49: =IFERROR(E49/C49,0) -> 0.01620974 | G49: Professional Services | H49: CC-6000 | I49: 6 | J49: =SUMIFS($D$4:$D$99,$B$4:$B$99,B49,$I$4:$I$99,"<="&I49) -> 422653 | K49: =IFERROR(J49/SUMIFS($C$4:$C$99,$B$4:$B$99,B49),0) -> 0.49579577
A50: Jun | B50: Customer Service | C50: 86148 | D50: 92514 | E50: =D50-C50 -> 6366 | F50: =IFERROR(E50/C50,0) -> 0.073896086 | G50: Payroll | H50: CC-7000 | I50: 6 | J50: =SUMIFS($D$4:$D$99,$B$4:$B$99,B50,$I$4:$I$99,"<="&I50) -> 540772 | K50: =IFERROR(J50/SUMIFS($C$4:$C$99,$B$4:$B$99,B50),0) -> 0.49743954
A51: Jun | B51: Executive | C51: 111485 | D51: 126467 | E51: =D51-C51 -> 14982 | F51: =IFERROR(E51/C51,0) -> 0.13438579 | G51: Payroll | H51: CC-8000 | I51: 6 | J51: =SUMIFS($D$4:$D$99,$B$4:$B$99,B51,$I$4:$I$99,"<="&I51) -> 695082 | K51: =IFERROR(J51/SUMIFS($C$4:$C$99,$B$4:$B$99,B51),0) -> 0.51887202 | L51: One-time expense pulled forward from a later month.
A52: Jul | B52: Sales | C52: 182916 | D52: 190823 | E52: =D52-C52 -> 7907 | F52: =IFERROR(E52/C52,0) -> 0.043227492 | G52: Payroll | H52: CC-1000 | I52: 7 | J52: =SUMIFS($D$4:$D$99,$B$4:$B$99,B52,$I$4:$I$99,"<="&I52) -> 1242594 | K52: =IFERROR(J52/SUMIFS($C$4:$C$99,$B$4:$B$99,B52),0) -> 0.56685717
A53: Jul | B53: Marketing | C53: 152430 | D53: 173057 | E53: =D53-C53 -> 20627 | F53: =IFERROR(E53/C53,0) -> 0.13532113 | G53: Marketing Spend | H53: CC-2000 | I53: 7 | J53: =SUMIFS($D$4:$D$99,$B$4:$B$99,B53,$I$4:$I$99,"<="&I53) -> 1121677 | K53: =IFERROR(J53/SUMIFS($C$4:$C$99,$B$4:$B$99,B53),0) -> 0.57066623 | L53: Overspend driven by higher contractor/vendor usage this month.
A54: Jul | B54: Operations | C54: 258440 | D54: 250971 | E54: =D54-C54 -> -7469 | F54: =IFERROR(E54/C54,0) -> -0.028900325 | G54: Payroll | H54: CC-3000 | I54: 7 | J54: =SUMIFS($D$4:$D$99,$B$4:$B$99,B54,$I$4:$I$99,"<="&I54) -> 1748591 | K54: =IFERROR(J54/SUMIFS($C$4:$C$99,$B$4:$B$99,B54),0) -> 0.55818999
A55: Jul | B55: IT | C55: 96539 | D55: 95246 | E55: =D55-C55 -> -1293 | F55: =IFERROR(E55/C55,0) -> -0.013393551 | G55: Software & IT | H55: CC-4400 | I55: 7 | J55: =SUMIFS($D$4:$D$99,$B$4:$B$99,B55,$I$4:$I$99,"<="&I55) -> 669186 | K55: =IFERROR(J55/SUMIFS($C$4:$C$99,$B$4:$B$99,B55),0) -> 0.57841629
A56: Jul | B56: HR | C56: 60972 | D56: 59298 | E56: =D56-C56 -> -1674 | F56: =IFERROR(E56/C56,0) -> -0.027455225 | G56: Payroll | H56: CC-5000 | I56: 7 | J56: =SUMIFS($D$4:$D$99,$B$4:$B$99,B56,$I$4:$I$99,"<="&I56) -> 418693 | K56: =IFERROR(J56/SUMIFS($C$4:$C$99,$B$4:$B$99,B56),0) -> 0.57300887
A57: Jul | B57: Finance | C57: 71134 | D57: 76108 | E57: =D57-C57 -> 4974 | F57: =IFERROR(E57/C57,0) -> 0.069924368 | G57: Professional Services | H57: CC-6000 | I57: 7 | J57: =SUMIFS($D$4:$D$99,$B$4:$B$99,B57,$I$4:$I$99,"<="&I57) -> 498761 | K57: =IFERROR(J57/SUMIFS($C$4:$C$99,$B$4:$B$99,B57),0) -> 0.58507474
A58: Jul | B58: Customer Service | C58: 86377 | D58: 80363 | E58: =D58-C58 -> -6014 | F58: =IFERROR(E58/C58,0) -> -0.069625016 | G58: Payroll | H58: CC-7000 | I58: 7 | J58: =SUMIFS($D$4:$D$99,$B$4:$B$99,B58,$I$4:$I$99,"<="&I58) -> 621135 | K58: =IFERROR(J58/SUMIFS($C$4:$C$99,$B$4:$B$99,B58),0) -> 0.571363
A59: Jul | B59: Executive | C59: 111782 | D59: 101825 | E59: =D59-C59 -> -9957 | F59: =IFERROR(E59/C59,0) -> -0.089075164 | G59: Payroll | H59: CC-8000 | I59: 7 | J59: =SUMIFS($D$4:$D$99,$B$4:$B$99,B59,$I$4:$I$99,"<="&I59) -> 796907 | K59: =IFERROR(J59/SUMIFS($C$4:$C$99,$B$4:$B$99,B59),0) -> 0.59488341
A60: Aug | B60: Sales | C60: 183402 | D60: 167462 | E60: =D60-C60 -> -15940 | F60: =IFERROR(E60/C60,0) -> -0.086912902 | G60: Payroll | H60: CC-1000 | I60: 8 | J60: =SUMIFS($D$4:$D$99,$B$4:$B$99,B60,$I$4:$I$99,"<="&I60) -> 1410056 | K60: =IFERROR(J60/SUMIFS($C$4:$C$99,$B$4:$B$99,B60),0) -> 0.64325142
A61: Aug | B61: Marketing | C61: 152835 | D61: 148267 | E61: =D61-C61 -> -4568 | F61: =IFERROR(E61/C61,0) -> -0.029888442 | G61: Marketing Spend | H61: CC-2000 | I61: 8 | J61: =SUMIFS($D$4:$D$99,$B$4:$B$99,B61,$I$4:$I$99,"<="&I61) -> 1269944 | K61: =IFERROR(J61/SUMIFS($C$4:$C$99,$B$4:$B$99,B61),0) -> 0.64609879
A62: Aug | B62: Operations | C62: 261817 | D62: 294958 | E62: =D62-C62 -> 33141 | F62: =IFERROR(E62/C62,0) -> 0.12658078 | G62: Payroll | H62: CC-3000 | I62: 8 | J62: =SUMIFS($D$4:$D$99,$B$4:$B$99,B62,$I$4:$I$99,"<="&I62) -> 2043549 | K62: =IFERROR(J62/SUMIFS($C$4:$C$99,$B$4:$B$99,B62),0) -> 0.65234729 | L62: One-time expense pulled forward from a later month.
A63: Aug | B63: IT | C63: 96795 | D63: 107291 | E63: =D63-C63 -> 10496 | F63: =IFERROR(E63/C63,0) -> 0.10843535 | G63: Software & IT | H63: CC-4400 | I63: 8 | J63: =SUMIFS($D$4:$D$99,$B$4:$B$99,B63,$I$4:$I$99,"<="&I63) -> 776477 | K63: =IFERROR(J63/SUMIFS($C$4:$C$99,$B$4:$B$99,B63),0) -> 0.67115413 | L63: Unplanned costs; department to provide a corrective action plan.
A64: Aug | B64: HR | C64: 61134 | D64: 56526 | E64: =D64-C64 -> -4608 | F64: =IFERROR(E64/C64,0) -> -0.075375405 | G64: Payroll | H64: CC-5000 | I64: 8 | J64: =SUMIFS($D$4:$D$99,$B$4:$B$99,B64,$I$4:$I$99,"<="&I64) -> 475219 | K64: =IFERROR(J64/SUMIFS($C$4:$C$99,$B$4:$B$99,B64),0) -> 0.65036842
A65: Aug | B65: Finance | C65: 71323 | D65: 64401 | E65: =D65-C65 -> -6922 | F65: =IFERROR(E65/C65,0) -> -0.097051442 | G65: Professional Services | H65: CC-6000 | I65: 8 | J65: =SUMIFS($D$4:$D$99,$B$4:$B$99,B65,$I$4:$I$99,"<="&I65) -> 563162 | K65: =IFERROR(J65/SUMIFS($C$4:$C$99,$B$4:$B$99,B65),0) -> 0.66062073
A66: Aug | B66: Customer Service | C66: 86606 | D66: 83856 | E66: =D66-C66 -> -2750 | F66: =IFERROR(E66/C66,0) -> -0.031752996 | G66: Payroll | H66: CC-7000 | I66: 8 | J66: =SUMIFS($D$4:$D$99,$B$4:$B$99,B66,$I$4:$I$99,"<="&I66) -> 704991 | K66: =IFERROR(J66/SUMIFS($C$4:$C$99,$B$4:$B$99,B66),0) -> 0.64849956
A67: Aug | B67: Executive | C67: 112079 | D67: 113748 | E67: =D67-C67 -> 1669 | F67: =IFERROR(E67/C67,0) -> 0.014891282 | G67: Payroll | H67: CC-8000 | I67: 8 | J67: =SUMIFS($D$4:$D$99,$B$4:$B$99,B67,$I$4:$I$99,"<="&I67) -> 910655 | K67: =IFERROR(J67/SUMIFS($C$4:$C$99,$B$4:$B$99,B67),0) -> 0.67979519
A68: Sep | B68: Sales | C68: 183888 | D68: 180536 | E68: =D68-C68 -> -3352 | F68: =IFERROR(E68/C68,0) -> -0.018228487 | G68: Payroll | H68: CC-1000 | I68: 9 | J68: =SUMIFS($D$4:$D$99,$B$4:$B$99,B68,$I$4:$I$99,"<="&I68) -> 1590592 | K68: =IFERROR(J68/SUMIFS($C$4:$C$99,$B$4:$B$99,B68),0) -> 0.72560988
A69: Sep | B69: Marketing | C69: 153240 | D69: 173425 | E69: =D69-C69 -> 20185 | F69: =IFERROR(E69/C69,0) -> 0.13172148 | G69: Marketing Spend | H69: CC-2000 | I69: 9 | J69: =SUMIFS($D$4:$D$99,$B$4:$B$99,B69,$I$4:$I$99,"<="&I69) -> 1443369 | K69: =IFERROR(J69/SUMIFS($C$4:$C$99,$B$4:$B$99,B69),0) -> 0.73433078 | L69: Unplanned costs; department to provide a corrective action plan.
A70: Sep | B70: Operations | C70: 258465 | D70: 290994 | E70: =D70-C70 -> 32529 | F70: =IFERROR(E70/C70,0) -> 0.12585456 | G70: Payroll | H70: CC-3000 | I70: 9 | J70: =SUMIFS($D$4:$D$99,$B$4:$B$99,B70,$I$4:$I$99,"<="&I70) -> 2334543 | K70: =IFERROR(J70/SUMIFS($C$4:$C$99,$B$4:$B$99,B70),0) -> 0.74523919 | L70: Unplanned costs; department to provide a corrective action plan.
A71: Sep | B71: IT | C71: 97052 | D71: 90004 | E71: =D71-C71 -> -7048 | F71: =IFERROR(E71/C71,0) -> -0.072620863 | G71: Software & IT | H71: CC-4400 | I71: 9 | J71: =SUMIFS($D$4:$D$99,$B$4:$B$99,B71,$I$4:$I$99,"<="&I71) -> 866481 | K71: =IFERROR(J71/SUMIFS($C$4:$C$99,$B$4:$B$99,B71),0) -> 0.74894981
A72: Sep | B72: HR | C72: 61296 | D72: 56128 | E72: =D72-C72 -> -5168 | F72: =IFERROR(E72/C72,0) -> -0.08431219 | G72: Payroll | H72: CC-5000 | I72: 9 | J72: =SUMIFS($D$4:$D$99,$B$4:$B$99,B72,$I$4:$I$99,"<="&I72) -> 531347 | K72: =IFERROR(J72/SUMIFS($C$4:$C$99,$B$4:$B$99,B72),0) -> 0.72718327
A73: Sep | B73: Finance | C73: 71512 | D73: 72801 | E73: =D73-C73 -> 1289 | F73: =IFERROR(E73/C73,0) -> 0.018024947 | G73: Professional Services | H73: CC-6000 | I73: 9 | J73: =SUMIFS($D$4:$D$99,$B$4:$B$99,B73,$I$4:$I$99,"<="&I73) -> 635963 | K73: =IFERROR(J73/SUMIFS($C$4:$C$99,$B$4:$B$99,B73),0) -> 0.74602041
A74: Sep | B74: Customer Service | C74: 86836 | D74: 90178 | E74: =D74-C74 -> 3342 | F74: =IFERROR(E74/C74,0) -> 0.038486342 | G74: Payroll | H74: CC-7000 | I74: 9 | J74: =SUMIFS($D$4:$D$99,$B$4:$B$99,B74,$I$4:$I$99,"<="&I74) -> 795169 | K74: =IFERROR(J74/SUMIFS($C$4:$C$99,$B$4:$B$99,B74),0) -> 0.73145153
A75: Sep | B75: Executive | C75: 112376 | D75: 119652 | E75: =D75-C75 -> 7276 | F75: =IFERROR(E75/C75,0) -> 0.064746921 | G75: Payroll | H75: CC-8000 | I75: 9 | J75: =SUMIFS($D$4:$D$99,$B$4:$B$99,B75,$I$4:$I$99,"<="&I75) -> 1030307 | K75: =IFERROR(J75/SUMIFS($C$4:$C$99,$B$4:$B$99,B75),0) -> 0.76911426
A76: Oct | B76: Sales | C76: 184374 | D76: 172650 | E76: =D76-C76 -> -11724 | F76: =IFERROR(E76/C76,0) -> -0.063588141 | G76: Payroll | H76: CC-1000 | I76: 10 | J76: =SUMIFS($D$4:$D$99,$B$4:$B$99,B76,$I$4:$I$99,"<="&I76) -> 1763242 | K76: =IFERROR(J76/SUMIFS($C$4:$C$99,$B$4:$B$99,B76),0) -> 0.80437083
A77: Oct | B77: Marketing | C77: 153645 | D77: 168191 | E77: =D77-C77 -> 14546 | F77: =IFERROR(E77/C77,0) -> 0.094672785 | G77: Marketing Spend | H77: CC-2000 | I77: 10 | J77: =SUMIFS($D$4:$D$99,$B$4:$B$99,B77,$I$4:$I$99,"<="&I77) -> 1611560 | K77: =IFERROR(J77/SUMIFS($C$4:$C$99,$B$4:$B$99,B77),0) -> 0.81989991
A78: Oct | B78: Operations | C78: 267260 | D78: 301413 | E78: =D78-C78 -> 34153 | F78: =IFERROR(E78/C78,0) -> 0.12778942 | G78: Payroll | H78: CC-3000 | I78: 10 | J78: =SUMIFS($D$4:$D$99,$B$4:$B$99,B78,$I$4:$I$99,"<="&I78) -> 2635956 | K78: =IFERROR(J78/SUMIFS($C$4:$C$99,$B$4:$B$99,B78),0) -> 0.84145707 | L78: Overspend driven by higher contractor/vendor usage this month.
A79: Oct | B79: IT | C79: 97308 | D79: 110789 | E79: =D79-C79 -> 13481 | F79: =IFERROR(E79/C79,0) -> 0.13853948 | G79: Software & IT | H79: CC-4400 | I79: 10 | J79: =SUMIFS($D$4:$D$99,$B$4:$B$99,B79,$I$4:$I$99,"<="&I79) -> 977270 | K79: =IFERROR(J79/SUMIFS($C$4:$C$99,$B$4:$B$99,B79),0) -> 0.84471117 | L79: Overspend driven by higher contractor/vendor usage this month.
A80: Oct | B80: HR | C80: 61458 | D80: 63544 | E80: =D80-C80 -> 2086 | F80: =IFERROR(E80/C80,0) -> 0.033941879 | G80: Payroll | H80: CC-5000 | I80: 10 | J80: =SUMIFS($D$4:$D$99,$B$4:$B$99,B80,$I$4:$I$99,"<="&I80) -> 594891 | K80: =IFERROR(J80/SUMIFS($C$4:$C$99,$B$4:$B$99,B80),0) -> 0.81414741
A81: Oct | B81: Finance | C81: 71701 | D81: 71693 | E81: =D81-C81 -> -8 | F81: =IFERROR(E81/C81,0) -> -0.00011157446 | G81: Professional Services | H81: CC-6000 | I81: 10 | J81: =SUMIFS($D$4:$D$99,$B$4:$B$99,B81,$I$4:$I$99,"<="&I81) -> 707656 | K81: =IFERROR(J81/SUMIFS($C$4:$C$99,$B$4:$B$99,B81),0) -> 0.83012033
A82: Oct | B82: Customer Service | C82: 87066 | D82: 90816 | E82: =D82-C82 -> 3750 | F82: =IFERROR(E82/C82,0) -> 0.043070774 | G82: Payroll | H82: CC-7000 | I82: 10 | J82: =SUMIFS($D$4:$D$99,$B$4:$B$99,B82,$I$4:$I$99,"<="&I82) -> 885985 | K82: =IFERROR(J82/SUMIFS($C$4:$C$99,$B$4:$B$99,B82),0) -> 0.81499037
A83: Oct | B83: Executive | C83: 112673 | D83: 118129 | E83: =D83-C83 -> 5456 | F83: =IFERROR(E83/C83,0) -> 0.048423313 | G83: Payroll | H83: CC-8000 | I83: 10 | J83: =SUMIFS($D$4:$D$99,$B$4:$B$99,B83,$I$4:$I$99,"<="&I83) -> 1148436 | K83: =IFERROR(J83/SUMIFS($C$4:$C$99,$B$4:$B$99,B83),0) -> 0.85729642
A84: Nov | B84: Sales | C84: 184860 | D84: 200789 | E84: =D84-C84 -> 15929 | F84: =IFERROR(E84/C84,0) -> 0.086167911 | G84: Payroll | H84: CC-1000 | I84: 11 | J84: =SUMIFS($D$4:$D$99,$B$4:$B$99,B84,$I$4:$I$99,"<="&I84) -> 1964031 | K84: =IFERROR(J84/SUMIFS($C$4:$C$99,$B$4:$B$99,B84),0) -> 0.89596848
A85: Nov | B85: Marketing | C85: 223372 | D85: 221427 | E85: =D85-C85 -> -1945 | F85: =IFERROR(E85/C85,0) -> -0.0087074477 | G85: Marketing Spend | H85: CC-2000 | I85: 11 | J85: =SUMIFS($D$4:$D$99,$B$4:$B$99,B85,$I$4:$I$99,"<="&I85) -> 1832987 | K85: =IFERROR(J85/SUMIFS($C$4:$C$99,$B$4:$B$99,B85),0) -> 0.93255347
A86: Nov | B86: Operations | C86: 285588 | D86: 319299 | E86: =D86-C86 -> 33711 | F86: =IFERROR(E86/C86,0) -> 0.11804067 | G86: Payroll | H86: CC-3000 | I86: 11 | J86: =SUMIFS($D$4:$D$99,$B$4:$B$99,B86,$I$4:$I$99,"<="&I86) -> 2955255 | K86: =IFERROR(J86/SUMIFS($C$4:$C$99,$B$4:$B$99,B86),0) -> 0.94338457 | L86: Unplanned costs; department to provide a corrective action plan.
A87: Nov | B87: IT | C87: 97565 | D87: 107950 | E87: =D87-C87 -> 10385 | F87: =IFERROR(E87/C87,0) -> 0.10644186 | G87: Software & IT | H87: CC-4400 | I87: 11 | J87: =SUMIFS($D$4:$D$99,$B$4:$B$99,B87,$I$4:$I$99,"<="&I87) -> 1085220 | K87: =IFERROR(J87/SUMIFS($C$4:$C$99,$B$4:$B$99,B87),0) -> 0.93801861 | L87: Unplanned costs; department to provide a corrective action plan.
A88: Nov | B88: HR | C88: 61620 | D88: 59974 | E88: =D88-C88 -> -1646 | F88: =IFERROR(E88/C88,0) -> -0.026712106 | G88: Payroll | H88: CC-5000 | I88: 11 | J88: =SUMIFS($D$4:$D$99,$B$4:$B$99,B88,$I$4:$I$99,"<="&I88) -> 654865 | K88: =IFERROR(J88/SUMIFS($C$4:$C$99,$B$4:$B$99,B88),0) -> 0.89622577
A89: Nov | B89: Finance | C89: 71890 | D89: 75416 | E89: =D89-C89 -> 3526 | F89: =IFERROR(E89/C89,0) -> 0.049047155 | G89: Professional Services | H89: CC-6000 | I89: 11 | J89: =SUMIFS($D$4:$D$99,$B$4:$B$99,B89,$I$4:$I$99,"<="&I89) -> 783072 | K89: =IFERROR(J89/SUMIFS($C$4:$C$99,$B$4:$B$99,B89),0) -> 0.91858755
A90: Nov | B90: Customer Service | C90: 104754 | D90: 109605 | E90: =D90-C90 -> 4851 | F90: =IFERROR(E90/C90,0) -> 0.046308494 | G90: Payroll | H90: CC-7000 | I90: 11 | J90: =SUMIFS($D$4:$D$99,$B$4:$B$99,B90,$I$4:$I$99,"<="&I90) -> 995590 | K90: =IFERROR(J90/SUMIFS($C$4:$C$99,$B$4:$B$99,B90),0) -> 0.91581264
A91: Nov | B91: Executive | C91: 112970 | D91: 121739 | E91: =D91-C91 -> 8769 | F91: =IFERROR(E91/C91,0) -> 0.077622378 | G91: Payroll | H91: CC-8000 | I91: 11 | J91: =SUMIFS($D$4:$D$99,$B$4:$B$99,B91,$I$4:$I$99,"<="&I91) -> 1270175 | K91: =IFERROR(J91/SUMIFS($C$4:$C$99,$B$4:$B$99,B91),0) -> 0.94817341
A92: Dec | B92: Sales | C92: 185346 | D92: 208963 | E92: =D92-C92 -> 23617 | F92: =IFERROR(E92/C92,0) -> 0.12742115 | G92: Payroll | H92: CC-1000 | I92: 12 | J92: =SUMIFS($D$4:$D$99,$B$4:$B$99,B92,$I$4:$I$99,"<="&I92) -> 2172994 | K92: =IFERROR(J92/SUMIFS($C$4:$C$99,$B$4:$B$99,B92),0) -> 0.99129501 | L92: Overspend driven by higher contractor/vendor usage this month.
A93: Dec | B93: Marketing | C93: 223960 | D93: 235186 | E93: =D93-C93 -> 11226 | F93: =IFERROR(E93/C93,0) -> 0.050125022 | G93: Marketing Spend | H93: CC-2000 | I93: 12 | J93: =SUMIFS($D$4:$D$99,$B$4:$B$99,B93,$I$4:$I$99,"<="&I93) -> 2068173 | K93: =IFERROR(J93/SUMIFS($C$4:$C$99,$B$4:$B$99,B93),0) -> 1.0522071
A94: Dec | B94: Operations | C94: 297892 | D94: 287023 | E94: =D94-C94 -> -10869 | F94: =IFERROR(E94/C94,0) -> -0.036486378 | G94: Payroll | H94: CC-3000 | I94: 12 | J94: =SUMIFS($D$4:$D$99,$B$4:$B$99,B94,$I$4:$I$99,"<="&I94) -> 3242278 | K94: =IFERROR(J94/SUMIFS($C$4:$C$99,$B$4:$B$99,B94),0) -> 1.0350088
A95: Dec | B95: IT | C95: 97822 | D95: 89946 | E95: =D95-C95 -> -7876 | F95: =IFERROR(E95/C95,0) -> -0.080513586 | G95: Software & IT | H95: CC-4400 | I95: 12 | J95: =SUMIFS($D$4:$D$99,$B$4:$B$99,B95,$I$4:$I$99,"<="&I95) -> 1175166 | K95: =IFERROR(J95/SUMIFS($C$4:$C$99,$B$4:$B$99,B95),0) -> 1.0157642
A96: Dec | B96: HR | C96: 61782 | D96: 59160 | E96: =D96-C96 -> -2622 | F96: =IFERROR(E96/C96,0) -> -0.042439545 | G96: Payroll | H96: CC-5000 | I96: 12 | J96: =SUMIFS($D$4:$D$99,$B$4:$B$99,B96,$I$4:$I$99,"<="&I96) -> 714025 | K96: =IFERROR(J96/SUMIFS($C$4:$C$99,$B$4:$B$99,B96),0) -> 0.97719012
A97: Dec | B97: Finance | C97: 72079 | D97: 74420 | E97: =D97-C97 -> 2341 | F97: =IFERROR(E97/C97,0) -> 0.032478253 | G97: Professional Services | H97: CC-6000 | I97: 12 | J97: =SUMIFS($D$4:$D$99,$B$4:$B$99,B97,$I$4:$I$99,"<="&I97) -> 857492 | K97: =IFERROR(J97/SUMIFS($C$4:$C$99,$B$4:$B$99,B97),0) -> 1.0058864
A98: Dec | B98: Customer Service | C98: 105029 | D98: 98472 | E98: =D98-C98 -> -6557 | F98: =IFERROR(E98/C98,0) -> -0.062430376 | G98: Payroll | H98: CC-7000 | I98: 12 | J98: =SUMIFS($D$4:$D$99,$B$4:$B$99,B98,$I$4:$I$99,"<="&I98) -> 1094062 | K98: =IFERROR(J98/SUMIFS($C$4:$C$99,$B$4:$B$99,B98),0) -> 1.006394
A99: Dec | B99: Executive | C99: 113267 | D99: 113045 | E99: =D99-C99 -> -222 | F99: =IFERROR(E99/C99,0) -> -0.0019599707 | G99: Payroll | H99: CC-8000 | I99: 12 | J99: =SUMIFS($D$4:$D$99,$B$4:$B$99,B99,$I$4:$I$99,"<="&I99) -> 1383220 | K99: =IFERROR(J99/SUMIFS($C$4:$C$99,$B$4:$B$99,B99),0) -> 1.0325604
A100: TOTAL | C100: =SUM(C4:C99) -> 12457049 | D100: =SUM(D4:D99) -> 12707410 | E100: =SUM(E4:E99) -> 250361 | F100: =IFERROR(E100/C100,0) -> 0.020097938 | J100: =D100 -> 12707410 | K100: =IFERROR(J100/C100,0) -> 1.0200979

Sheet Variance Report
A1: FY2027 Budget vs. Actual Variance Report
A2: All figures pull live from Revenue Detail and Expense Detail via SUMIF.
A4: Revenue Variance by Product Line
A5: Product Line | B5: Budgeted Revenue | C5: Actual Revenue | D5: Variance $ | E5: Variance %
A6: Apparel | B6: =SUMIF('Revenue Detail'!$C$4:$C$195,A6,'Revenue Detail'!$F$4:$F$195) -> 4845883 | C6: =SUMIF('Revenue Detail'!$C$4:$C$195,A6,'Revenue Detail'!$I$4:$I$195) -> 4995971.7 | D6: =C6-B6 -> 150088.61 | E6: =IFERROR(D6/B6,0) -> 0.030972396
A7: Home Goods | B7: =SUMIF('Revenue Detail'!$C$4:$C$195,A7,'Revenue Detail'!$F$4:$F$195) -> 4199798.7 | C7: =SUMIF('Revenue Detail'!$C$4:$C$195,A7,'Revenue Detail'!$I$4:$I$195) -> 4264274.9 | D7: =C7-B7 -> 64476.19 | E7: =IFERROR(D7/B7,0) -> 0.01535221
A8: Electronics | B8: =SUMIF('Revenue Detail'!$C$4:$C$195,A8,'Revenue Detail'!$F$4:$F$195) -> 5923115 | C8: =SUMIF('Revenue Detail'!$C$4:$C$195,A8,'Revenue Detail'!$I$4:$I$195) -> 6003090.7 | D8: =C8-B8 -> 79975.72 | E8: =IFERROR(D8/B8,0) -> 0.013502307
A9: Outdoor | B9: =SUMIF('Revenue Detail'!$C$4:$C$195,A9,'Revenue Detail'!$F$4:$F$195) -> 4092029.4 | C9: =SUMIF('Revenue Detail'!$C$4:$C$195,A9,'Revenue Detail'!$I$4:$I$195) -> 4105308.8 | D9: =C9-B9 -> 13279.46 | E9: =IFERROR(D9/B9,0) -> 0.0032452015
A10: Total Revenue | B10: =SUM(B6:B9) -> 19060826 | C10: =SUM(C6:C9) -> 19368646 | D10: =C10-B10 -> 307819.98 | E10: =IFERROR(D10/B10,0) -> 0.016149351
A12: Expense Variance by Department
A13: Department | B13: Budgeted Amount | C13: Actual Amount | D13: Variance $ | E13: Variance %
A14: Sales | B14: =SUMIF('Expense Detail'!$B$4:$B$99,A14,'Expense Detail'!$C$4:$C$99) -> 2192076 | C14: =SUMIF('Expense Detail'!$B$4:$B$99,A14,'Expense Detail'!$D$4:$D$99) -> 2172994 | D14: =C14-B14 -> -19082 | E14: =IFERROR(D14/B14,0) -> -0.0087049902
A15: Marketing | B15: =SUMIF('Expense Detail'!$B$4:$B$99,A15,'Expense Detail'!$C$4:$C$99) -> 1965557 | C15: =SUMIF('Expense Detail'!$B$4:$B$99,A15,'Expense Detail'!$D$4:$D$99) -> 2068173 | D15: =C15-B15 -> 102616 | E15: =IFERROR(D15/B15,0) -> 0.052207084
A16: Operations | B16: =SUMIF('Expense Detail'!$B$4:$B$99,A16,'Expense Detail'!$C$4:$C$99) -> 3132609 | C16: =SUMIF('Expense Detail'!$B$4:$B$99,A16,'Expense Detail'!$D$4:$D$99) -> 3242278 | D16: =C16-B16 -> 109669 | E16: =IFERROR(D16/B16,0) -> 0.035008838
A17: IT | B17: =SUMIF('Expense Detail'!$B$4:$B$99,A17,'Expense Detail'!$C$4:$C$99) -> 1156928 | C17: =SUMIF('Expense Detail'!$B$4:$B$99,A17,'Expense Detail'!$D$4:$D$99) -> 1175166 | D17: =C17-B17 -> 18238 | E17: =IFERROR(D17/B17,0) -> 0.015764162
A18: HR | B18: =SUMIF('Expense Detail'!$B$4:$B$99,A18,'Expense Detail'!$C$4:$C$99) -> 730692 | C18: =SUMIF('Expense Detail'!$B$4:$B$99,A18,'Expense Detail'!$D$4:$D$99) -> 714025 | D18: =C18-B18 -> -16667 | E18: =IFERROR(D18/B18,0) -> -0.022809884
A19: Finance | B19: =SUMIF('Expense Detail'!$B$4:$B$99,A19,'Expense Detail'!$C$4:$C$99) -> 852474 | C19: =SUMIF('Expense Detail'!$B$4:$B$99,A19,'Expense Detail'!$D$4:$D$99) -> 857492 | D19: =C19-B19 -> 5018 | E19: =IFERROR(D19/B19,0) -> 0.0058863965
A20: Customer Service | B20: =SUMIF('Expense Detail'!$B$4:$B$99,A20,'Expense Detail'!$C$4:$C$99) -> 1087111 | C20: =SUMIF('Expense Detail'!$B$4:$B$99,A20,'Expense Detail'!$D$4:$D$99) -> 1094062 | D20: =C20-B20 -> 6951 | E20: =IFERROR(D20/B20,0) -> 0.0063940113
A21: Executive | B21: =SUMIF('Expense Detail'!$B$4:$B$99,A21,'Expense Detail'!$C$4:$C$99) -> 1339602 | C21: =SUMIF('Expense Detail'!$B$4:$B$99,A21,'Expense Detail'!$D$4:$D$99) -> 1383220 | D21: =C21-B21 -> 43618 | E21: =IFERROR(D21/B21,0) -> 0.032560417
A22: Total Expense | B22: =SUM(B14:B21) -> 12457049 | C22: =SUM(C14:C21) -> 12707410 | D22: =C22-B22 -> 250361 | E22: =IFERROR(D22/B22,0) -> 0.020097938
A24: Net Operating Income Summary
A25: Budgeted Revenue | E25: =B10 -> 19060826
A26: Budgeted Expense | E26: =B22 -> 12457049
A27: Budgeted Net Operating Income | E27: =E25-E26 -> 6603777.1
A28: Actual Revenue | E28: =C10 -> 19368646
A29: Actual Expense | E29: =C22 -> 12707410
A30: Actual Net Operating Income | E30: =E28-E29 -> 6661236.1
A31: NOI Variance $ | E31: =E30-E27 -> 57458.98
A32: NOI Variance % | E32: =IFERROR(E31/E27,0) -> 0.0087009266

Sheet Cash Flow Forecast
A1: FY2027 Cash Flow Forecast — Scenario Planning
A2: Driven by the Active Planning Scenario on the Assumptions tab — change it there to re-forecast.
A3: Active Scenario: | C3: =Assumptions!$B$19 -> Likely Case
A4: Revenue Multiplier: | C4: =Assumptions!$B$26 -> 1
A5: Expense Multiplier: | C5: =Assumptions!$B$27 -> 1
A7: Month | B7: Beginning Cash | C7: Cash Receipts | D7: Operating Disbursements | E7: Capital Expenditures | F7: Debt Service | G7: Ending Cash Balance
A8: Jan | B8: =Assumptions!$D$15 -> 850000 | C8: =SUMIF('Revenue Detail'!$A$4:$A$195,A8,'Revenue Detail'!$F$4:$F$195)*Assumptions!$D$14*Assumptions!$B$26 -> 1159305.6 | D8: =SUMIF('Expense Detail'!$A$4:$A$99,A8,'Expense Detail'!$C$4:$C$99)*Assumptions!$B$27 -> 1008120 | E8: 15000 | F8: =Assumptions!$D$16 -> 15000 | G8: =B8+C8-D8-E8-F8 -> 971185.6
A9: Feb | B9: =G8 -> 971185.6 | C9: =SUMIF('Revenue Detail'!$A$4:$A$195,A9,'Revenue Detail'!$F$4:$F$195)*Assumptions!$D$14*Assumptions!$B$26 -> 1190555.3 | D9: =SUMIF('Expense Detail'!$A$4:$A$99,A9,'Expense Detail'!$C$4:$C$99)*Assumptions!$B$27 -> 995120 | E9: 15000 | F9: =Assumptions!$D$16 -> 15000 | G9: =B9+C9-D9-E9-F9 -> 1136620.9
A10: Mar | B10: =G9 -> 1136620.9 | C10: =SUMIF('Revenue Detail'!$A$4:$A$195,A10,'Revenue Detail'!$F$4:$F$195)*Assumptions!$D$14*Assumptions!$B$26 -> 1321441.2 | D10: =SUMIF('Expense Detail'!$A$4:$A$99,A10,'Expense Detail'!$C$4:$C$99)*Assumptions!$B$27 -> 1003771 | E10: 20000 | F10: =Assumptions!$D$16 -> 15000 | G10: =B10+C10-D10-E10-F10 -> 1419291.1
A11: Apr | B11: =G10 -> 1419291.1 | C11: =SUMIF('Revenue Detail'!$A$4:$A$195,A11,'Revenue Detail'!$F$4:$F$195)*Assumptions!$D$14*Assumptions!$B$26 -> 1395818.8 | D11: =SUMIF('Expense Detail'!$A$4:$A$99,A11,'Expense Detail'!$C$4:$C$99)*Assumptions!$B$27 -> 1009794 | E11: 150000 | F11: =Assumptions!$D$16 -> 15000 | G11: =B11+C11-D11-E11-F11 -> 1640315.9
A12: May | B12: =G11 -> 1640315.9 | C12: =SUMIF('Revenue Detail'!$A$4:$A$195,A12,'Revenue Detail'!$F$4:$F$195)*Assumptions!$D$14*Assumptions!$B$26 -> 1427871.7 | D12: =SUMIF('Expense Detail'!$A$4:$A$99,A12,'Expense Detail'!$C$4:$C$99)*Assumptions!$B$27 -> 1013832 | E12: 40000 | F12: =Assumptions!$D$16 -> 15000 | G12: =B12+C12-D12-E12-F12 -> 1999355.7
A13: Jun | B13: =G12 -> 1999355.7 | C13: =SUMIF('Revenue Detail'!$A$4:$A$195,A13,'Revenue Detail'!$F$4:$F$195)*Assumptions!$D$14*Assumptions!$B$26 -> 1503153.4 | D13: =SUMIF('Expense Detail'!$A$4:$A$99,A13,'Expense Detail'!$C$4:$C$99)*Assumptions!$B$27 -> 1019885 | E13: 20000 | F13: =Assumptions!$D$16 -> 15000 | G13: =B13+C13-D13-E13-F13 -> 2447624.1
A14: Jul | B14: =G13 -> 2447624.1 | C14: =SUMIF('Revenue Detail'!$A$4:$A$195,A14,'Revenue Detail'!$F$4:$F$195)*Assumptions!$D$14*Assumptions!$B$26 -> 1463613.5 | D14: =SUMIF('Expense Detail'!$A$4:$A$99,A14,'Expense Detail'!$C$4:$C$99)*Assumptions!$B$27 -> 1020590 | E14: 15000 | F14: =Assumptions!$D$16 -> 15000 | G14: =B14+C14-D14-E14-F14 -> 2860647.6
A15: Aug | B15: =G14 -> 2860647.6 | C15: =SUMIF('Revenue Detail'!$A$4:$A$195,A15,'Revenue Detail'!$F$4:$F$195)*Assumptions!$D$14*Assumptions!$B$26 -> 1524668.6 | D15: =SUMIF('Expense Detail'!$A$4:$A$99,A15,'Expense Detail'!$C$4:$C$99)*Assumptions!$B$27 -> 1025991 | E15: 15000 | F15: =Assumptions!$D$16 -> 15000 | G15: =B15+C15-D15-E15-F15 -> 3329325.1
A16: Sep | B16: =G15 -> 3329325.1 | C16: =SUMIF('Revenue Detail'!$A$4:$A$195,A16,'Revenue Detail'!$F$4:$F$195)*Assumptions!$D$14*Assumptions!$B$26 -> 1442009.1 | D16: =SUMIF('Expense Detail'!$A$4:$A$99,A16,'Expense Detail'!$C$4:$C$99)*Assumptions!$B$27 -> 1024665 | E16: 60000 | F16: =Assumptions!$D$16 -> 15000 | G16: =B16+C16-D16-E16-F16 -> 3671669.2
A17: Oct | B17: =G16 -> 3671669.2 | C17: =SUMIF('Revenue Detail'!$A$4:$A$195,A17,'Revenue Detail'!$F$4:$F$195)*Assumptions!$D$14*Assumptions!$B$26 -> 1619014.4 | D17: =SUMIF('Expense Detail'!$A$4:$A$99,A17,'Expense Detail'!$C$4:$C$99)*Assumptions!$B$27 -> 1035485 | E17: 90000 | F17: =Assumptions!$D$16 -> 15000 | G17: =B17+C17-D17-E17-F17 -> 4150198.6
A18: Nov | B18: =G17 -> 4150198.6 | C18: =SUMIF('Revenue Detail'!$A$4:$A$195,A18,'Revenue Detail'!$F$4:$F$195)*Assumptions!$D$14*Assumptions!$B$26 -> 1999584.4 | D18: =SUMIF('Expense Detail'!$A$4:$A$99,A18,'Expense Detail'!$C$4:$C$99)*Assumptions!$B$27 -> 1142619 | E18: 20000 | F18: =Assumptions!$D$16 -> 15000 | G18: =B18+C18-D18-E18-F18 -> 4972164
A19: Dec | B19: =G18 -> 4972164 | C19: =SUMIF('Revenue Detail'!$A$4:$A$195,A19,'Revenue Detail'!$F$4:$F$195)*Assumptions!$D$14*Assumptions!$B$26 -> 2251357 | D19: =SUMIF('Expense Detail'!$A$4:$A$99,A19,'Expense Detail'!$C$4:$C$99)*Assumptions!$B$27 -> 1157177 | E19: 15000 | F19: =Assumptions!$D$16 -> 15000 | G19: =B19+C19-D19-E19-F19 -> 6036344.1
A20: FY2027 TOTAL | C20: =SUM(C8:C19) -> 18298393 | D20: =SUM(D8:D19) -> 12457049 | E20: =SUM(E8:E19) -> 475000 | F20: =SUM(F8:F19) -> 180000 | G20: =G19 -> 6036344.1

Sheet Headcount Plan
A1: Headcount & Compensation Plan — FY2027
A2: Benefits Load % is applied on top of base salary to estimate fully-loaded monthly cost.
A4: Department | B4: Role | C4: Headcount | D4: Avg. Annual Salary | E4: Benefits Load % | F4: Fully-Loaded Monthly Cost
A5: Sales | B5: Sales Representative | C5: 12 | D5: 58000 | E5: 0.28 | F5: =C5*D5/12*(1+E5) -> 74240
A6: Sales | B6: Sales Manager | C6: 3 | D6: 85000 | E6: 0.28 | F6: =C6*D6/12*(1+E6) -> 27200
A7: Marketing | B7: Marketing Specialist | C7: 5 | D7: 62000 | E7: 0.28 | F7: =C7*D7/12*(1+E7) -> 33066.667
A8: Marketing | B8: Marketing Manager | C8: 2 | D8: 90000 | E8: 0.28 | F8: =C8*D8/12*(1+E8) -> 19200
A9: Operations | B9: Warehouse Associate | C9: 20 | D9: 42000 | E9: 0.28 | F9: =C9*D9/12*(1+E9) -> 89600
A10: Operations | B10: Operations Supervisor | C10: 4 | D10: 68000 | E10: 0.28 | F10: =C10*D10/12*(1+E10) -> 29013.333
A11: IT | B11: Software Engineer | C11: 6 | D11: 105000 | E11: 0.28 | F11: =C11*D11/12*(1+E11) -> 67200
A12: IT | B12: IT Support Specialist | C12: 3 | D12: 55000 | E12: 0.28 | F12: =C12*D12/12*(1+E12) -> 17600
A13: HR | B13: HR Generalist | C13: 3 | D13: 60000 | E13: 0.28 | F13: =C13*D13/12*(1+E13) -> 19200
A14: HR | B14: HR Director | C14: 1 | D14: 120000 | E14: 0.28 | F14: =C14*D14/12*(1+E14) -> 12800
A15: Finance | B15: Financial Analyst | C15: 4 | D15: 72000 | E15: 0.28 | F15: =C15*D15/12*(1+E15) -> 30720
A16: Finance | B16: Controller | C16: 1 | D16: 115000 | E16: 0.28 | F16: =C16*D16/12*(1+E16) -> 12266.667
... A20: Executive | B20: Chief Executive Officer | C20: 1 | D20: 250000 | E20: 0.28 | F20: =C20*D20/12*(1+E20) -> 26666.667
A21: TOTAL | C21: =SUM(C5:C20) -> 80 | D21: =AVERAGE(D5:D20) -> 91250 | F21: =SUM(F5:F20) -> 571413.33
A23: Note: fully-loaded monthly payroll cost above rolls up into the "Payroll" component of each department's line in Expense Detail; figures on that tab are entered independently by Finance each budget cycle.

Sheet Dashboard
A1: Meridian North Retail Co. — FY2027 Budget Dashboard
A2: All figures link live to Revenue Detail, Expense Detail, and the Variance Report.
A4: TOTAL REVENUE | C4: TOTAL EXPENSE | E4: NET OPERATING INCOME | G4: NOI VARIANCE
A5: ='Variance Report'!C10 -> 19368646 | C5: ='Variance Report'!C22 -> 12707410 | E5: ='Variance Report'!E30 -> 6661236.1 | G5: ='Variance Report'!E31 -> 57458.98
A6: ="Budget "&TEXT('Variance Report'!B10,"$#,##0")&" · "&TEXT(('Variance Report'!C10-'Variance Report'!B10)/'Variance Report'!B10,"+0.0%;-0.0%")&" vs. plan" -> Budget $19,060,826 · +1.6% vs. plan | C6: ="Budget "&TEXT('Variance Report'!B22,"$#,##0")&" · "&TEXT(('Variance Report'!C22-'Variance Report'!B22)/'Variance Report'!B22,"+0.0%;-0.0%")&" vs. plan" -> Budget $12,457,049 · +2.0% vs. plan | E6: ="Budget "&TEXT('Variance Report'!E27,"$#,##0")&" · "&TEXT('Variance Report'!E32,"+0.0%;-0.0%")&" vs. plan" -> Budget $6,603,777 · +0.9% vs. plan | G6: =IF('Variance Report'!E31>=0,"▲ ","▼ ")&TEXT('Variance Report'!E32,"+0.0%;-0.0%")&" vs. budgeted NOI" -> ▲ +0.9% vs. budgeted NOI
A8: Monthly Revenue: Budget vs. Actual | E8: Actual Expense by Department
A9: Month | B9: Budgeted Revenue | C9: Actual Revenue | D9: Trend | E9: Department | F9: Actual Expense | G9: Trend
A10: Jan | B10: =SUMIF('Revenue Detail'!$A$4:$A$195,A10,'Revenue Detail'!$F$4:$F$195) -> 1207610 | C10: =SUMIF('Revenue Detail'!$A$4:$A$195,A10,'Revenue Detail'!$I$4:$I$195) -> 1228606.7 | D10: =REPT("█",ROUND(C10/MAX($C$10:$C$21)*12,0)) -> ██████ | E10: Sales | F10: =SUMIF('Expense Detail'!$B$4:$B$99,E10,'Expense Detail'!$D$4:$D$99) -> 2172994 | G10: =REPT("█",ROUND(F10/MAX($F$10:$F$17)*12,0)) -> ████████
A11: Feb | B11: =SUMIF('Revenue Detail'!$A$4:$A$195,A11,'Revenue Detail'!$F$4:$F$195) -> 1240161.8 | C11: =SUMIF('Revenue Detail'!$A$4:$A$195,A11,'Revenue Detail'!$I$4:$I$195) -> 1267158 | D11: =REPT("█",ROUND(C11/MAX($C$10:$C$21)*12,0)) -> ██████ | E11: Marketing | F11: =SUMIF('Expense Detail'!$B$4:$B$99,E11,'Expense Detail'!$D$4:$D$99) -> 2068173 | G11: =REPT("█",ROUND(F11/MAX($F$10:$F$17)*12,0)) -> ████████
A12: Mar | B12: =SUMIF('Revenue Detail'!$A$4:$A$195,A12,'Revenue Detail'!$F$4:$F$195) -> 1376501.3 | C12: =SUMIF('Revenue Detail'!$A$4:$A$195,A12,'Revenue Detail'!$I$4:$I$195) -> 1426009.7 | D12: =REPT("█",ROUND(C12/MAX($C$10:$C$21)*12,0)) -> ███████ | E12: Operations | F12: =SUMIF('Expense Detail'!$B$4:$B$99,E12,'Expense Detail'!$D$4:$D$99) -> 3242278 | G12: =REPT("█",ROUND(F12/MAX($F$10:$F$17)*12,0)) -> ████████████
A13: Apr | B13: =SUMIF('Revenue Detail'!$A$4:$A$195,A13,'Revenue Detail'!$F$4:$F$195) -> 1453977.9 | C13: =SUMIF('Revenue Detail'!$A$4:$A$195,A13,'Revenue Detail'!$I$4:$I$195) -> 1461741.9 | D13: =REPT("█",ROUND(C13/MAX($C$10:$C$21)*12,0)) -> ███████ | E13: IT | F13: =SUMIF('Expense Detail'!$B$4:$B$99,E13,'Expense Detail'!$D$4:$D$99) -> 1175166 | G13: =REPT("█",ROUND(F13/MAX($F$10:$F$17)*12,0)) -> ████
A14: May | B14: =SUMIF('Revenue Detail'!$A$4:$A$195,A14,'Revenue Detail'!$F$4:$F$195) -> 1487366.4 | C14: =SUMIF('Revenue Detail'!$A$4:$A$195,A14,'Revenue Detail'!$I$4:$I$195) -> 1475662.3 | D14: =REPT("█",ROUND(C14/MAX($C$10:$C$21)*12,0)) -> ███████ | E14: HR | F14: =SUMIF('Expense Detail'!$B$4:$B$99,E14,'Expense Detail'!$D$4:$D$99) -> 714025 | G14: =REPT("█",ROUND(F14/MAX($F$10:$F$17)*12,0)) -> ███
A15: Jun | B15: =SUMIF('Revenue Detail'!$A$4:$A$195,A15,'Revenue Detail'!$F$4:$F$195) -> 1565784.8 | C15: =SUMIF('Revenue Detail'!$A$4:$A$195,A15,'Revenue Detail'!$I$4:$I$195) -> 1625131.8 | D15: =REPT("█",ROUND(C15/MAX($C$10:$C$21)*12,0)) -> ████████ | E15: Finance | F15: =SUMIF('Expense Detail'!$B$4:$B$99,E15,'Expense Detail'!$D$4:$D$99) -> 857492 | G15: =REPT("█",ROUND(F15/MAX($F$10:$F$17)*12,0)) -> ███
A16: Jul | B16: =SUMIF('Revenue Detail'!$A$4:$A$195,A16,'Revenue Detail'!$F$4:$F$195) -> 1524597.4 | C16: =SUMIF('Revenue Detail'!$A$4:$A$195,A16,'Revenue Detail'!$I$4:$I$195) -> 1549051.6 | D16: =REPT("█",ROUND(C16/MAX($C$10:$C$21)*12,0)) -> ████████ | E16: Customer Service | F16: =SUMIF('Expense Detail'!$B$4:$B$99,E16,'Expense Detail'!$D$4:$D$99) -> 1094062 | G16: =REPT("█",ROUND(F16/MAX($F$10:$F$17)*12,0)) -> ████
A17: Aug | B17: =SUMIF('Revenue Detail'!$A$4:$A$195,A17,'Revenue Detail'!$F$4:$F$195) -> 1588196.4 | C17: =SUMIF('Revenue Detail'!$A$4:$A$195,A17,'Revenue Detail'!$I$4:$I$195) -> 1608495.1 | D17: =REPT("█",ROUND(C17/MAX($C$10:$C$21)*12,0)) -> ████████ | E17: Executive | F17: =SUMIF('Expense Detail'!$B$4:$B$99,E17,'Expense Detail'!$D$4:$D$99) -> 1383220 | G17: =REPT("█",ROUND(F17/MAX($F$10:$F$17)*12,0)) -> █████
A18: Sep | B18: =SUMIF('Revenue Detail'!$A$4:$A$195,A18,'Revenue Detail'!$F$4:$F$195) -> 1502092.8 | C18: =SUMIF('Revenue Detail'!$A$4:$A$195,A18,'Revenue Detail'!$I$4:$I$195) -> 1506837.1 | D18: =REPT("█",ROUND(C18/MAX($C$10:$C$21)*12,0)) -> ████████
A19: Oct | B19: =SUMIF('Revenue Detail'!$A$4:$A$195,A19,'Revenue Detail'!$F$4:$F$195) -> 1686473.3 | C19: =SUMIF('Revenue Detail'!$A$4:$A$195,A19,'Revenue Detail'!$I$4:$I$195) -> 1710714.7 | D19: =REPT("█",ROUND(C19/MAX($C$10:$C$21)*12,0)) -> █████████
A20: Nov | B20: =SUMIF('Revenue Detail'!$A$4:$A$195,A20,'Revenue Detail'!$F$4:$F$195) -> 2082900.4 | C20: =SUMIF('Revenue Detail'!$A$4:$A$195,A20,'Revenue Detail'!$I$4:$I$195) -> 2106741.7 | D20: =REPT("█",ROUND(C20/MAX($C$10:$C$21)*12,0)) -> ███████████
A21: Dec | B21: =SUMIF('Revenue Detail'!$A$4:$A$195,A21,'Revenue Detail'!$F$4:$F$195) -> 2345163.6 | C21: =SUMIF('Revenue Detail'!$A$4:$A$195,A21,'Revenue Detail'!$I$4:$I$195) -> 2402495.6 | D21: =REPT("█",ROUND(C21/MAX($C$10:$C$21)*12,0)) -> ████████████

Sheet Assumptions
A1: Meridian North Retail Co. — FY2027 Budget Assumptions & Drivers
A2: Blue cells are editable inputs. Yellow fill marks key planning levers.
A4: Revenue Growth Assumptions (FY2027 vs. FY2026 Actual)
A5: Product Line | B5: FY2026 Actual Revenue | C5: FY2027 Growth Rate
A6: Apparel | B6: 4750000 | C6: 0.045
A7: Home Goods | B7: 3100000 | C7: 0.03
A8: Electronics | B8: 4200000 | C8: 0.06
A9: Outdoor | B9: 2650000 | C9: 0.05
A11: Cost & Operating Assumptions
A12: Expense Inflation Rate (FY2027 vs. FY2026) | D12: 0.032
A13: Effective Tax Rate | D13: 0.24
A14: Cash Collection Rate (% of monthly revenue collected same month) | D14: 0.96
A15: Starting Cash Balance (Jan 1, 2027) | D15: 850000
A16: Monthly Debt Service Payment | D16: 15000
A18: Scenario Planning
A19: Active Planning Scenario: | B19: Likely Case
A21: Scenario | B21: Revenue Multiplier | C21: Expense Multiplier
A22: Best Case | B22: 1.08 | C22: 0.97
A23: Likely Case | B23: 1 | C23: 1
A24: Worst Case | B24: 0.9 | C24: 1.05
A26: Selected Revenue Multiplier | B26: =INDEX($B$22:$B$24,MATCH($B$19,$A$22:$A$24,0)) -> 1
A27: Selected Expense Multiplier | B27: =INDEX($C$22:$C$24,MATCH($B$19,$A$22:$A$24,0)) -> 1

Sheet Budget Request Form
A1: FY2027 Department Budget Request Form
A3: Department: | B3: IT | F3: Cost Center Code: | G3: CC-4410
A4: Submitted By: | B4: J. Alvarez, IT Director | F4: Date Submitted: | G4: 2026-09-15
A6: Instructions: select your Department above, then enter a monthly dollar request for each expense category you need funded. Blue/yellow cells are editable; the FY2027 Total and grand total at the bottom recalculate automatically. Submit one form per department per budget cycle.
A8: Expense Category | B8: Jan | C8: Feb | D8: Mar | E8: Apr | F8: May | G8: Jun | H8: Jul | I8: Aug | J8: Sep | K8: Oct | L8: Nov | M8: Dec | N8: FY2027 Total | O8: Notes / Justification
A9: EXAMPLE — Software & IT | B9: 7200 | C9: 7200 | D9: 7400 | E9: 7400 | F9: 7600 | G9: 7600 | H9: 7800 | I9: 7800 | J9: 8000 | K9: 8000 | L9: 8200 | M9: 8600 | N9: =SUM(B9:M9) -> 92800 | O9: Includes SaaS license renewals (Q1) and two new laptop refresh batches (Q3/Q4).
N10: =SUM(B10:M10) -> 0
N11: =SUM(B11:M11) -> 0
N12: =SUM(B12:M12) -> 0
N13: =SUM(B13:M13) -> 0
N14: =SUM(B14:M14) -> 0
N15: =SUM(B15:M15) -> 0
A16: TOTAL DEPARTMENT REQUEST | B16: =SUM(B9:B15) -> 7200 | C16: =SUM(C9:C15) -> 7200 | D16: =SUM(D9:D15) -> 7400 | E16: =SUM(E9:E15) -> 7400 | F16: =SUM(F9:F15) -> 7600 | G16: =SUM(G9:G15) -> 7600 | H16: =SUM(H9:H15) -> 7800 | I16: =SUM(I9:I15) -> 7800 | ... N16: =SUM(N9:N15) -> 92800
